[{"id":10020,"league":{"id":34,"name":"Brasileirão Serie B","country":"Brazil","is_women":false,"current_season":{"id":52,"name":"Brasileiro Serie B 2026","year":2026,"start_date":"2026-01-01","end_date":"2026-12-31"}},"home_team":"Operário-PR","away_team":"Grêmio Novorizontino","home_team_obj":{"id":828,"name":"Operário-PR","short_name":"Operário-PR","country":"Brazil","coach":{"name":"Luizinho Lopes","shortName":"L. Lopes"},"venue":{"id":621,"name":"Estádio Germano Krüger","city":"Ponta Grossa","country":"Brazil","capacity":10632}},"away_team_obj":{"id":836,"name":"Grêmio Novorizontino","short_name":"Novorizontino","country":"Brazil","coach":{"name":"Enderson Moreira","shortName":"E. Moreira"},"venue":{"id":628,"name":"Estádio Dr. Jorge Ismael de Biasi","city":"Novo Horizonte","country":"Brazil","capacity":14096}},"event_date":"2026-07-12T18:00:00+04:00","group_name":null,"status":"2nd_half","home_score":2,"away_score":1,"home_score_ht":1,"away_score_ht":1,"penalty_shootout":null,"extra_time_score":null,"current_minute":93,"period":"2T","home_xg_live":0.53,"away_xg_live":2.53,"incidents":[{"text":"Second half","type":"period","minute":90,"is_live":true,"added_time":999,"away_score":1,"home_score":2},{"type":"injuryTime","length":5,"minute":90},{"type":"substitution","minute":87,"is_home":false,"player_in":"R. Barcellos","added_time":null,"player_out":"Rômulo","player_in_id":1466533,"player_out_id":1105078},{"type":"substitution","minute":82,"is_home":true,"player_in":"Índio","added_time":null,"player_out":"V. D. D. Antonia","player_in_id":981621,"player_out_id":1652832},{"type":"substitution","minute":81,"is_home":true,"player_in":"C. Dantas","added_time":null,"player_out":"Pablo","player_in_id":869574,"player_out_id":374486},{"type":"substitution","minute":78,"is_home":false,"player_in":"M. Bianqui","added_time":null,"player_out":"L. Naldi","player_in_id":981746,"player_out_id":1101061},{"type":"substitution","minute":78,"is_home":false,"player_in":"Carlão","added_time":null,"player_out":"Luís Oyama","player_in_id":922564,"player_out_id":922570},{"type":"card","minute":78,"player":"G. Boschilia","is_home":true,"card_type":"yellow","player_id":358540,"added_time":null},{"type":"substitution","minute":75,"is_home":true,"player_in":"Aylon","added_time":null,"player_out":"H. Pereira","player_in_id":364528,"player_out_id":352880},{"type":"substitution","minute":72,"is_home":true,"player_in":"F. Augusto","added_time":null,"player_out":"N. Paraíba","player_in_id":847089,"player_out_id":1148584},{"type":"card","minute":67,"player":"Pablo","is_home":true,"card_type":"yellow","player_id":374486,"added_time":null},{"type":"substitution","minute":65,"is_home":false,"player_in":"C. Ortíz","added_time":null,"player_out":"Vinicius Paiva","player_in_id":293235,"player_out_id":990160},{"type":"substitution","minute":65,"is_home":false,"player_in":"Tavinho","added_time":null,"player_out":"Reidiney","player_in_id":1836636,"player_out_id":1647542},{"type":"goal","minute":61,"player":"G. Boschilia","is_home":true,"sequence":[{"gk":{"x":99.8,"y":50.2},"gm":{"x":44.62,"y":77.83},"pid":358540,"pos":{"x":99.5,"y":0.5},"body":"left-foot","event":"goal","player":"G. Boschilia"}],"goal_type":"regular","player_id":358540,"added_time":null,"away_score":1,"home_score":2},{"type":"card","minute":51,"player":"Reidiney","is_home":false,"card_type":"yellow","player_id":1647542,"added_time":null},{"text":"HT","type":"period","minute":45,"is_live":false,"added_time":999,"away_score":1,"home_score":1},{"type":"injuryTime","length":5,"minute":45},{"type":"goal","assist":"Rômulo","minute":35,"player":"Robson","is_home":false,"sequence":[{"end":{"x":14.4,"y":90.6},"pid":922570,"pos":{"x":33.6,"y":94.2},"event":"pass","player":"Luís Oyama"},{"end":{"x":3.1,"y":48.5},"pid":1105078,"pos":{"x":14.4,"y":90.6},"event":"ball-movement","player":"Rômulo"},{"end":{"x":3.1,"y":48.5},"pid":1105078,"pos":{"x":2.3,"y":72.6},"event":"pass","assist":true,"player":"Rômulo"},{"gk":{"x":1.5,"y":55.2},"gm":{"x":40.32,"y":78.83},"pid":850987,"pos":{"x":3.1,"y":48.5},"body":"left-foot","event":"goal","player":"Robson"}],"goal_type":"regular","player_id":850987,"added_time":null,"away_score":1,"home_score":1},{"type":"goal","minute":23,"player":"G. Boschilia","is_home":true,"sequence":[{"gk":{"x":100,"y":50.4},"gm":{"x":66.67,"y":55.67},"pid":358540,"pos":{"x":74.4,"y":47.7},"body":"left-foot","event":"goal","player":"G. Boschilia"}],"goal_type":"regular","player_id":358540,"added_time":null,"away_score":0,"home_score":1},{"type":"varDecision","minute":4,"player":"Pablo","is_home":true,"decision":"goalAwarded","confirmed":false,"player_id":374486,"added_time":null}],"live_stats":{"away":{"duels":53,"fouls":18,"passes":302,"crosses":"7/19 (37%)","punches":0,"tackles":12,"dribbles":"4/8 (50%)","offsides":2,"throw_ins":25,"clearances":10,"free_kicks":20,"goal_kicks":5,"long_balls":"13/43 (30%)","recoveries":37,"big_chances":3,"high_claims":1,"tackles_won":33,"total_saves":2,"total_shots":12,"aerial_duels":"12/24 (50%)","corner_kicks":2,"dispossessed":5,"ground_duels":"36/67 (54%)","hit_woodwork":1,"yellow_cards":1,"blocked_shots":2,"interceptions":8,"total_tackles":12,"expected_goals":2.21,"accurate_passes":245,"ball_possession":44,"goals_prevented":-1.52,"shots_on_target":5,"goalkeeper_saves":2,"shots_inside_box":8,"shots_off_target":5,"final_third_phase":"61/96 (64%)","shots_outside_box":4,"big_chances_missed":2,"big_chances_scored":1,"final_third_entries":58,"errors_lead_to_a_goal":1,"fouled_in_final_third":4,"touches_in_penalty_area":18},"home":{"duels":47,"fouls":20,"passes":400,"crosses":"2/19 (11%)","punches":2,"tackles":10,"dribbles":"5/12 (42%)","offsides":3,"throw_ins":22,"clearances":21,"free_kicks":18,"goal_kicks":9,"long_balls":"28/51 (55%)","recoveries":34,"big_chances":1,"high_claims":0,"tackles_won":60,"total_saves":4,"total_shots":10,"aerial_duels":"12/24 (50%)","corner_kicks":10,"dispossessed":6,"ground_duels":"32/70 (46%)","hit_woodwork":0,"yellow_cards":2,"blocked_shots":3,"interceptions":6,"total_tackles":10,"expected_goals":0.49,"accurate_passes":335,"ball_possession":56,"goals_prevented":1.43,"shots_on_target":4,"goalkeeper_saves":4,"shots_inside_box":1,"shots_off_target":3,"final_third_phase":"45/64 (70%)","shots_outside_box":9,"big_chances_missed":1,"big_chances_scored":0,"final_third_entries":37,"errors_lead_to_a_goal":0,"fouled_in_final_third":1,"touches_in_penalty_area":5},"first_half":{"away":{"duels":54,"fouls":8,"passes":169,"crosses":"5/10 (50%)","tackles":5,"dribbles":"3/4 (75%)","offsides":0,"throw_ins":15,"clearances":4,"free_kicks":10,"goal_kicks":4,"long_balls":"9/24 (38%)","recoveries":23,"big_chances":3,"tackles_won":20,"total_saves":0,"total_shots":7,"aerial_duels":"3/8 (38%)","corner_kicks":0,"dispossessed":2,"ground_duels":"18/31 (58%)","hit_woodwork":1,"yellow_cards":0,"blocked_shots":1,"interceptions":6,"total_tackles":5,"expected_goals":2.07,"accurate_passes":135,"ball_possession":45,"shots_on_target":3,"goalkeeper_saves":0,"shots_inside_box":6,"shots_off_target":3,"shots_outside_box":1,"big_chances_missed":2,"big_chances_scored":1,"final_third_entries":33,"fouled_in_final_third":2},"home":{"duels":46,"fouls":10,"passes":211,"crosses":"1/8 (13%)","tackles":3,"dribbles":"3/7 (43%)","offsides":2,"throw_ins":9,"clearances":11,"free_kicks":8,"goal_kicks":5,"long_balls":"12/24 (50%)","recoveries":21,"big_chances":0,"tackles_won":67,"total_saves":2,"total_shots":4,"aerial_duels":"5/8 (63%)","corner_kicks":4,"dispossessed":1,"ground_duels":"13/31 (42%)","hit_woodwork":0,"yellow_cards":0,"blocked_shots":1,"interceptions":4,"total_tackles":3,"expected_goals":0.16,"accurate_passes":176,"ball_possession":55,"shots_on_target":1,"goalkeeper_saves":2,"shots_inside_box":0,"shots_off_target":2,"shots_outside_box":4,"big_chances_missed":0,"big_chances_scored":0,"final_third_entries":21,"fouled_in_final_third":1}},"second_half":{"away":{"duels":52,"fouls":10,"passes":133,"crosses":"2/9 (22%)","tackles":7,"dribbles":"1/4 (25%)","offsides":2,"throw_ins":10,"clearances":6,"free_kicks":10,"goal_kicks":1,"long_balls":"4/19 (21%)","recoveries":14,"big_chances":0,"tackles_won":43,"total_saves":2,"total_shots":5,"aerial_duels":"9/16 (56%)","corner_kicks":2,"dispossessed":3,"ground_duels":"18/36 (50%)","hit_woodwork":0,"yellow_cards":1,"blocked_shots":1,"interceptions":2,"total_tackles":7,"expected_goals":0.14,"accurate_passes":110,"ball_possession":42,"shots_on_target":2,"goalkeeper_saves":2,"shots_inside_box":2,"shots_off_target":2,"shots_outside_box":3,"big_chances_missed":0,"big_chances_scored":0,"final_third_entries":25,"fouled_in_final_third":2},"home":{"duels":47,"fouls":10,"passes":189,"crosses":"1/11 (9%)","tackles":7,"dribbles":"2/5 (40%)","offsides":1,"throw_ins":13,"clearances":10,"free_kicks":10,"goal_kicks":4,"long_balls":"16/27 (59%)","recoveries":13,"big_chances":1,"tackles_won":57,"total_saves":2,"total_shots":6,"aerial_duels":"7/16 (44%)","corner_kicks":6,"dispossessed":5,"ground_duels":"19/39 (49%)","hit_woodwork":0,"yellow_cards":2,"blocked_shots":2,"interceptions":2,"total_tackles":7,"expected_goals":0.33,"accurate_passes":159,"ball_possession":58,"shots_on_target":3,"goalkeeper_saves":2,"shots_inside_box":1,"shots_off_target":1,"shots_outside_box":5,"big_chances_missed":1,"big_chances_scored":0,"final_third_entries":16,"fouled_in_final_third":0}}}},{"id":46393,"league":{"id":26,"name":"Allsvenskan","country":"Sweden","is_women":false,"current_season":{"id":9,"name":"Allsvenskan 2026","year":2026,"start_date":"2026-01-01","end_date":"2026-12-31"}},"home_team":"GAIS","away_team":"IF Elfsborg","home_team_obj":{"id":448,"name":"GAIS","short_name":"GAIS","country":"Sweden","coach":{"name":"Fredrik Holmberg","shortName":"F. Holmberg"},"venue":null},"away_team_obj":{"id":440,"name":"IF Elfsborg","short_name":"Elfsborg","country":"Sweden","coach":{"name":"Björn Hamberg","shortName":"B. Hamberg"},"venue":{"id":419,"name":"Borås Arena","city":"Boras","country":"Sweden","capacity":17800}},"event_date":"2026-07-12T18:30:00+04:00","group_name":null,"status":"2nd_half","home_score":1,"away_score":0,"home_score_ht":0,"away_score_ht":0,"penalty_shootout":null,"extra_time_score":null,"current_minute":70,"period":"2T","home_xg_live":null,"away_xg_live":null,"incidents":[{"text":"Second half","type":"period","minute":90,"is_live":true,"added_time":999,"away_score":0,"home_score":1},{"type":"substitution","minute":70,"is_home":false,"player_in":"A. Zeneli","added_time":null,"player_out":"A. Sigurpálsson","player_in_id":227892,"player_out_id":990395},{"type":"substitution","minute":70,"is_home":false,"player_in":"T. Silverholt","added_time":null,"player_out":"M. I. Kamara","player_in_id":981043,"player_out_id":2138619},{"type":"substitution","minute":68,"is_home":true,"player_in":"O. Pettersson","added_time":null,"player_out":"J. Fagerjord","player_in_id":825906,"player_out_id":1021081},{"type":"substitution","minute":68,"is_home":true,"player_in":"R. Frej","added_time":null,"player_out":"A. Wängberg","player_in_id":1184134,"player_out_id":153309},{"type":"substitution","minute":59,"is_home":false,"player_in":"L. Östman","added_time":null,"player_out":"F. Ihler","player_in_id":1800434,"player_out_id":1035693},{"type":"substitution","minute":59,"is_home":false,"player_in":"M. Rohdén","added_time":null,"player_out":"S. Olsson","player_in_id":209082,"player_out_id":850851},{"type":"goal","assist":"R. Niklasson","minute":51,"player":"R. F. Thorkelsson","is_home":true,"sequence":[{"end":{"x":85.4,"y":79.9},"pid":1047960,"pos":{"x":94.1,"y":84.5},"event":"pass","player":"M. d. Brienne"},{"end":{"x":87.9,"y":51},"pid":1471077,"pos":{"x":84.7,"y":73.8},"event":"cross","assist":true,"player":"R. Niklasson"},{"gk":{"x":98.8,"y":51.1},"gm":{"x":67.2,"y":73.67},"pid":1153236,"pos":{"x":93.2,"y":49},"body":"right-foot","event":"goal","player":"R. F. Thorkelsson"}],"goal_type":"regular","player_id":1153236,"added_time":null,"away_score":0,"home_score":1},{"type":"substitution","minute":46,"is_home":true,"player_in":"H. Sletsjoe","added_time":null,"player_out":"M. Andersson","player_in_id":1022179,"player_out_id":1184132},{"text":"HT","type":"period","minute":45,"is_live":false,"added_time":999,"away_score":0,"home_score":0},{"type":"card","minute":27,"player":"O. Ågren","is_home":true,"card_type":"yellow","player_id":1172500,"added_time":null}],"live_stats":{"away":{"duels":62,"fouls":4,"passes":427,"crosses":"6/10 (60%)","punches":2,"tackles":16,"dribbles":"5/9 (56%)","offsides":1,"throw_ins":10,"clearances":18,"free_kicks":4,"goal_kicks":7,"long_balls":"25/48 (52%)","recoveries":38,"big_chances":1,"tackles_won":56,"total_saves":3,"total_shots":12,"aerial_duels":"9/14 (64%)","corner_kicks":3,"dispossessed":8,"ground_duels":"25/41 (61%)","hit_woodwork":1,"yellow_cards":0,"blocked_shots":5,"interceptions":5,"through_balls":1,"total_tackles":16,"accurate_passes":371,"ball_possession":54,"shots_on_target":3,"goalkeeper_saves":3,"shots_inside_box":10,"shots_off_target":4,"final_third_phase":"72/96 (75%)","shots_outside_box":2,"big_chances_missed":1,"final_third_entries":46,"fouled_in_final_third":1,"touches_in_penalty_area":21},"home":{"duels":38,"fouls":4,"passes":365,"crosses":"4/11 (36%)","punches":0,"tackles":12,"dribbles":"0/4 (0%)","offsides":0,"throw_ins":12,"clearances":8,"free_kicks":4,"goal_kicks":7,"long_balls":"21/47 (45%)","recoveries":37,"big_chances":0,"tackles_won":67,"total_saves":3,"total_shots":12,"aerial_duels":"5/14 (36%)","corner_kicks":4,"dispossessed":12,"ground_duels":"16/41 (39%)","hit_woodwork":0,"yellow_cards":1,"blocked_shots":2,"interceptions":4,"through_balls":0,"total_tackles":12,"accurate_passes":301,"ball_possession":46,"shots_on_target":5,"goalkeeper_saves":3,"shots_inside_box":7,"shots_off_target":5,"final_third_phase":"87/123 (71%)","shots_outside_box":5,"big_chances_missed":0,"final_third_entries":51,"fouled_in_final_third":2,"touches_in_penalty_area":18},"first_half":{"away":{"duels":62,"fouls":3,"passes":321,"crosses":"5/6 (83%)","tackles":13,"dribbles":"3/6 (50%)","offsides":1,"throw_ins":7,"clearances":10,"free_kicks":3,"goal_kicks":4,"long_balls":"20/36 (56%)","recoveries":26,"big_chances":1,"tackles_won":54,"total_saves":3,"total_shots":6,"aerial_duels":"5/9 (56%)","corner_kicks":2,"dispossessed":5,"ground_duels":"19/30 (63%)","hit_woodwork":1,"yellow_cards":0,"blocked_shots":1,"interceptions":4,"through_balls":1,"total_tackles":13,"accurate_passes":282,"ball_possession":61,"shots_on_target":2,"goalkeeper_saves":3,"shots_inside_box":5,"shots_off_target":3,"shots_outside_box":1,"big_chances_missed":1,"final_third_entries":34,"fouled_in_final_third":1},"home":{"duels":38,"fouls":3,"passes":202,"crosses":"3/7 (43%)","tackles":8,"dribbles":"0/1 (0%)","offsides":0,"throw_ins":5,"clearances":3,"free_kicks":3,"goal_kicks":6,"long_balls":"12/26 (46%)","recoveries":27,"big_chances":0,"tackles_won":75,"total_saves":2,"total_shots":10,"aerial_duels":"4/9 (44%)","corner_kicks":2,"dispossessed":12,"ground_duels":"11/30 (37%)","hit_woodwork":0,"yellow_cards":1,"blocked_shots":2,"interceptions":4,"through_balls":0,"total_tackles":8,"accurate_passes":163,"ball_possession":39,"shots_on_target":4,"goalkeeper_saves":2,"shots_inside_box":5,"shots_off_target":4,"shots_outside_box":5,"big_chances_missed":0,"final_third_entries":31,"fouled_in_final_third":1}},"second_half":{"away":{"duels":62,"fouls":1,"passes":106,"crosses":"1/4 (25%)","tackles":3,"dribbles":"2/3 (67%)","offsides":0,"throw_ins":3,"clearances":8,"free_kicks":1,"goal_kicks":3,"long_balls":"5/12 (42%)","recoveries":12,"big_chances":0,"tackles_won":67,"total_saves":0,"total_shots":6,"aerial_duels":"4/5 (80%)","corner_kicks":1,"dispossessed":3,"ground_duels":"6/11 (55%)","hit_woodwork":0,"yellow_cards":0,"blocked_shots":4,"interceptions":1,"through_balls":0,"total_tackles":3,"accurate_passes":89,"ball_possession":39,"shots_on_target":1,"goalkeeper_saves":0,"shots_inside_box":5,"shots_off_target":1,"shots_outside_box":1,"big_chances_missed":0,"final_third_entries":12,"fouled_in_final_third":0},"home":{"duels":38,"fouls":1,"passes":163,"crosses":"1/4 (25%)","tackles":4,"dribbles":"0/3 (0%)","offsides":0,"throw_ins":7,"clearances":5,"free_kicks":1,"goal_kicks":1,"long_balls":"9/21 (43%)","recoveries":10,"big_chances":0,"tackles_won":50,"total_saves":1,"total_shots":2,"aerial_duels":"1/5 (20%)","corner_kicks":2,"dispossessed":0,"ground_duels":"5/11 (45%)","hit_woodwork":0,"yellow_cards":0,"blocked_shots":0,"interceptions":0,"through_balls":0,"total_tackles":4,"accurate_passes":138,"ball_possession":61,"shots_on_target":1,"goalkeeper_saves":1,"shots_inside_box":2,"shots_off_target":1,"shots_outside_box":0,"big_chances_missed":0,"final_third_entries":20,"fouled_in_final_third":1}}}},{"id":46395,"league":{"id":26,"name":"Allsvenskan","country":"Sweden","is_women":false,"current_season":{"id":9,"name":"Allsvenskan 2026","year":2026,"start_date":"2026-01-01","end_date":"2026-12-31"}},"home_team":"IF Brommapojkarna","away_team":"IK Sirius","home_team_obj":{"id":437,"name":"IF Brommapojkarna","short_name":"BP","country":"Sweden","coach":{"name":"Ulf Kristiansson","shortName":"U. Kristiansson"},"venue":{"id":417,"name":"Grimsta IP","city":"Stockholm","country":"Sweden","capacity":7343}},"away_team_obj":{"id":447,"name":"IK Sirius","short_name":"Sirius","country":"Sweden","coach":{"name":"Andreas Engelmark","shortName":"A. Engelmark"},"venue":{"id":426,"name":"Studenternas IP","city":"Uppsala","country":"Sweden","capacity":11167}},"event_date":"2026-07-12T18:30:00+04:00","group_name":null,"status":"2nd_half","home_score":1,"away_score":2,"home_score_ht":0,"away_score_ht":2,"penalty_shootout":null,"extra_time_score":null,"current_minute":70,"period":"2T","home_xg_live":null,"away_xg_live":null,"incidents":[{"text":"Second half","type":"period","minute":90,"is_live":true,"added_time":999,"away_score":2,"home_score":1},{"type":"substitution","minute":64,"is_home":true,"player_in":"K. Barslund","added_time":null,"player_out":"M. W. Derbali","player_in_id":1083373,"player_out_id":1410421},{"type":"substitution","minute":61,"is_home":false,"player_in":"C. Nilden","added_time":null,"player_out":"V. Svensson","player_in_id":1424610,"player_out_id":1429793},{"type":"goal","assist":"M. K. Hansen","minute":47,"player":"A. Troelsen","is_home":true,"sequence":[{"end":{"x":94.8,"y":56},"pid":976386,"pos":{"x":99.5,"y":0.5},"event":"cross","assist":true,"player":"M. K. Hansen"},{"gk":{"x":99.4,"y":51.6},"gm":{"x":43.01,"y":61},"pid":1159436,"pos":{"x":96.4,"y":57.7},"body":"head","event":"goal","player":"A. Troelsen"}],"goal_type":"regular","player_id":1159436,"added_time":null,"away_score":2,"home_score":1},{"text":"HT","type":"period","minute":45,"is_live":false,"added_time":999,"away_score":2,"home_score":0},{"type":"goal","assist":"O. Krusnell","minute":40,"player":"R. Ure","is_home":false,"sequence":[{"end":{"x":9.4,"y":44.5},"pid":825897,"pos":{"x":12.6,"y":39.7},"event":"pass","assist":true,"player":"O. Krusnell"},{"gk":{"x":1.9,"y":49.3},"gm":{"x":41.4,"y":69.33},"pid":1142351,"pos":{"x":9.4,"y":44.5},"body":"left-foot","event":"goal","player":"R. Ure"}],"goal_type":"regular","player_id":1142351,"added_time":null,"away_score":2,"home_score":0},{"type":"goal","minute":18,"player":"I. Bjerkebo","is_home":false,"sequence":[{"gk":{"x":3.3,"y":48},"gm":{"x":62.37,"y":48.33},"pid":1142230,"pos":{"x":28.6,"y":36.6},"body":"right-foot","event":"goal","player":"I. Bjerkebo"}],"goal_type":"regular","player_id":1142230,"added_time":null,"away_score":1,"home_score":0}],"live_stats":{"away":{"duels":40,"fouls":12,"passes":454,"crosses":"4/15 (27%)","punches":0,"tackles":10,"dribbles":"3/6 (50%)","throw_ins":13,"clearances":4,"free_kicks":7,"goal_kicks":4,"long_balls":"18/29 (62%)","recoveries":29,"high_claims":1,"tackles_won":80,"total_saves":3,"total_shots":11,"aerial_duels":"2/9 (22%)","corner_kicks":7,"dispossessed":5,"ground_duels":"19/44 (43%)","hit_woodwork":0,"blocked_shots":2,"interceptions":12,"total_tackles":10,"accurate_passes":404,"ball_possession":51,"shots_on_target":6,"goalkeeper_saves":3,"shots_inside_box":7,"shots_off_target":3,"final_third_phase":"89/123 (72%)","shots_outside_box":4,"final_third_entries":45,"errors_lead_to_a_goal":0,"fouled_in_final_third":1,"touches_in_penalty_area":24},"home":{"duels":58,"fouls":7,"passes":448,"crosses":"2/6 (33%)","punches":3,"tackles":8,"dribbles":"5/9 (56%)","throw_ins":11,"clearances":21,"free_kicks":12,"goal_kicks":6,"long_balls":"19/34 (56%)","recoveries":31,"high_claims":0,"tackles_won":63,"total_saves":3,"total_shots":7,"aerial_duels":"7/9 (78%)","corner_kicks":2,"dispossessed":6,"ground_duels":"24/44 (55%)","hit_woodwork":0,"blocked_shots":2,"interceptions":4,"total_tackles":8,"accurate_passes":405,"ball_possession":49,"shots_on_target":3,"goalkeeper_saves":3,"shots_inside_box":3,"shots_off_target":2,"final_third_phase":"97/112 (87%)","shots_outside_box":4,"final_third_entries":40,"errors_lead_to_a_goal":1,"fouled_in_final_third":1,"touches_in_penalty_area":9},"first_half":{"away":{"duels":39,"fouls":9,"passes":323,"crosses":"1/7 (14%)","tackles":9,"dribbles":"1/2 (50%)","throw_ins":10,"clearances":2,"free_kicks":3,"goal_kicks":3,"long_balls":"12/18 (67%)","recoveries":21,"tackles_won":78,"total_saves":0,"total_shots":7,"aerial_duels":"0/4 (0%)","corner_kicks":3,"dispossessed":4,"ground_duels":"13/29 (45%)","hit_woodwork":0,"blocked_shots":2,"interceptions":11,"total_tackles":9,"accurate_passes":287,"ball_possession":50,"shots_on_target":4,"goalkeeper_saves":0,"shots_inside_box":5,"shots_off_target":1,"shots_outside_box":2,"final_third_entries":32,"fouled_in_final_third":0},"home":{"duels":61,"fouls":3,"passes":318,"crosses":"1/3 (33%)","tackles":5,"dribbles":"2/6 (33%)","throw_ins":7,"clearances":10,"free_kicks":9,"goal_kicks":3,"long_balls":"10/23 (43%)","recoveries":25,"tackles_won":80,"total_saves":2,"total_shots":2,"aerial_duels":"4/4 (100%)","corner_kicks":1,"dispossessed":5,"ground_duels":"16/29 (55%)","hit_woodwork":0,"blocked_shots":0,"interceptions":3,"total_tackles":5,"accurate_passes":282,"ball_possession":50,"shots_on_target":0,"goalkeeper_saves":2,"shots_inside_box":1,"shots_off_target":2,"shots_outside_box":1,"final_third_entries":27,"fouled_in_final_third":0}},"second_half":{"away":{"duels":40,"fouls":3,"passes":131,"crosses":"3/8 (38%)","tackles":1,"dribbles":"2/4 (50%)","throw_ins":3,"clearances":2,"free_kicks":4,"goal_kicks":1,"long_balls":"6/11 (55%)","recoveries":8,"tackles_won":100,"total_saves":3,"total_shots":4,"aerial_duels":"2/5 (40%)","corner_kicks":4,"dispossessed":1,"ground_duels":"6/15 (40%)","hit_woodwork":0,"blocked_shots":0,"interceptions":1,"total_tackles":1,"accurate_passes":117,"ball_possession":51,"shots_on_target":2,"goalkeeper_saves":3,"shots_inside_box":2,"shots_off_target":2,"shots_outside_box":2,"final_third_entries":13,"fouled_in_final_third":1},"home":{"duels":55,"fouls":4,"passes":130,"crosses":"1/3 (33%)","tackles":3,"dribbles":"3/3 (100%)","throw_ins":4,"clearances":11,"free_kicks":3,"goal_kicks":3,"long_balls":"9/11 (82%)","recoveries":6,"tackles_won":33,"total_saves":1,"total_shots":5,"aerial_duels":"3/5 (60%)","corner_kicks":1,"dispossessed":1,"ground_duels":"8/15 (53%)","hit_woodwork":0,"blocked_shots":2,"interceptions":1,"total_tackles":3,"accurate_passes":123,"ball_possession":49,"shots_on_target":3,"goalkeeper_saves":1,"shots_inside_box":2,"shots_off_target":0,"shots_outside_box":3,"final_third_entries":13,"fouled_in_final_third":1}}}},{"id":207009,"league":{"id":54,"name":"Eliteserien","country":"Norway","is_women":false,"current_season":{"id":1230,"name":"Eliteserien 2026","year":2026,"start_date":"2026-01-01","end_date":"2026-12-31"}},"home_team":"Sandefjord Fotball","away_team":"HamKam","home_team_obj":{"id":2085,"name":"Sandefjord Fotball","short_name":"Sandefjord","country":"Norway","coach":{"name":"Andreas Ulrik Tegstrom","shortName":"A. U. Tegstrom"},"venue":null},"away_team_obj":{"id":2075,"name":"HamKam","short_name":"HamKam","country":"Norway","coach":{"name":"Thomas Myhre","shortName":"T. Myhre"},"venue":null},"event_date":"2026-07-12T19:00:00+04:00","group_name":null,"status":"halftime","home_score":1,"away_score":0,"home_score_ht":1,"away_score_ht":0,"penalty_shootout":null,"extra_time_score":null,"current_minute":45,"period":"HT","home_xg_live":0.98,"away_xg_live":0.15,"incidents":[{"text":"HT","type":"period","minute":45,"is_live":false,"added_time":999,"away_score":0,"home_score":1},{"type":"card","minute":39,"player":"E. Amundsen-Day","is_home":false,"card_type":"yellow","player_id":1122200,"added_time":null},{"type":"card","minute":27,"player":"F. C. Pedersen","is_home":true,"card_type":"yellow","player_id":1046317,"added_time":null},{"type":"goal","assist":"V. W. Egeli","minute":4,"player":"B. Berntsen","is_home":true,"sequence":[{"end":{"x":45.8,"y":60.8},"pid":1486976,"pos":{"x":44.2,"y":73.5},"event":"pass","player":"S. Kristiansen"},{"end":{"x":57.1,"y":20.6},"pid":1386504,"pos":{"x":52.3,"y":44.8},"event":"pass","player":"J. Vester"},{"end":{"x":68.9,"y":18.5},"pid":956798,"pos":{"x":57.1,"y":20.6},"event":"pass","player":"S. Mork"},{"end":{"x":83.6,"y":47},"pid":1046317,"pos":{"x":70.2,"y":20.6},"event":"pass","player":"F. C. Pedersen"},{"end":{"x":92.6,"y":58.8},"pid":1121442,"pos":{"x":88,"y":49.6},"event":"pass","assist":true,"player":"V. W. Egeli"},{"gk":{"x":99,"y":50},"gm":{"x":64.52,"y":89.5},"pid":2162448,"pos":{"x":92.6,"y":58.8},"body":"right-foot","event":"goal","player":"B. Berntsen"}],"goal_type":"regular","player_id":2162448,"added_time":null,"away_score":0,"home_score":1}],"live_stats":{"away":{"duels":59,"fouls":7,"passes":196,"crosses":"3/9 (33%)","punches":1,"tackles":6,"dribbles":"1/3 (33%)","throw_ins":8,"clearances":20,"free_kicks":9,"goal_kicks":7,"long_balls":"17/29 (59%)","recoveries":18,"tackles_won":50,"total_saves":1,"total_shots":3,"aerial_duels":"12/16 (75%)","corner_kicks":1,"dispossessed":1,"ground_duels":"15/30 (50%)","hit_woodwork":0,"yellow_cards":1,"blocked_shots":2,"interceptions":3,"total_tackles":6,"expected_goals":0.15,"accurate_passes":158,"ball_possession":41,"goals_prevented":-0.11,"shots_on_target":0,"goalkeeper_saves":1,"shots_inside_box":3,"shots_off_target":1,"final_third_phase":"21/33 (64%)","shots_outside_box":0,"final_third_entries":18,"fouled_in_final_third":1,"touches_in_penalty_area":8},"home":{"duels":43,"fouls":9,"passes":285,"crosses":"2/13 (15%)","punches":0,"tackles":4,"dribbles":"4/6 (67%)","throw_ins":12,"clearances":11,"free_kicks":7,"goal_kicks":2,"long_balls":"13/27 (48%)","recoveries":17,"tackles_won":100,"total_saves":0,"total_shots":9,"aerial_duels":"5/16 (31%)","corner_kicks":3,"dispossessed":4,"ground_duels":"15/30 (50%)","hit_woodwork":1,"yellow_cards":1,"blocked_shots":4,"interceptions":3,"total_tackles":4,"expected_goals":0.98,"accurate_passes":252,"ball_possession":59,"goals_prevented":0.0,"shots_on_target":2,"goalkeeper_saves":0,"shots_inside_box":5,"shots_off_target":3,"final_third_phase":"65/83 (78%)","shots_outside_box":4,"final_third_entries":29,"fouled_in_final_third":0,"touches_in_penalty_area":13},"first_half":{"away":{"duels":59,"fouls":7,"passes":196,"crosses":"3/9 (33%)","tackles":6,"dribbles":"1/3 (33%)","throw_ins":8,"clearances":20,"free_kicks":9,"goal_kicks":7,"long_balls":"17/29 (59%)","recoveries":18,"tackles_won":50,"total_saves":1,"total_shots":3,"aerial_duels":"12/16 (75%)","corner_kicks":1,"dispossessed":1,"ground_duels":"15/30 (50%)","hit_woodwork":0,"yellow_cards":1,"blocked_shots":2,"interceptions":3,"total_tackles":6,"expected_goals":0.15,"accurate_passes":158,"ball_possession":41,"shots_on_target":0,"goalkeeper_saves":1,"shots_inside_box":3,"shots_off_target":1,"shots_outside_box":0,"final_third_entries":18,"fouled_in_final_third":1},"home":{"duels":43,"fouls":9,"passes":285,"crosses":"2/13 (15%)","tackles":4,"dribbles":"4/6 (67%)","throw_ins":12,"clearances":11,"free_kicks":7,"goal_kicks":2,"long_balls":"13/27 (48%)","recoveries":17,"tackles_won":100,"total_saves":0,"total_shots":9,"aerial_duels":"5/16 (31%)","corner_kicks":3,"dispossessed":4,"ground_duels":"15/30 (50%)","hit_woodwork":1,"yellow_cards":1,"blocked_shots":4,"interceptions":3,"total_tackles":4,"expected_goals":0.98,"accurate_passes":252,"ball_possession":59,"shots_on_target":2,"goalkeeper_saves":0,"shots_inside_box":5,"shots_off_target":3,"shots_outside_box":4,"final_third_entries":29,"fouled_in_final_third":0}}}},{"id":207007,"league":{"id":54,"name":"Eliteserien","country":"Norway","is_women":false,"current_season":{"id":1230,"name":"Eliteserien 2026","year":2026,"start_date":"2026-01-01","end_date":"2026-12-31"}},"home_team":"Rosenborg BK","away_team":"Kristiansund BK","home_team_obj":{"id":2078,"name":"Rosenborg BK","short_name":"Rosenborg","country":"Norway","coach":{"name":"Freyr Alexandersson","shortName":"F. Alexandersson"},"venue":null},"away_team_obj":{"id":2079,"name":"Kristiansund BK","short_name":"Kristiansund","country":"Norway","coach":{"name":"Amund Skiri","shortName":"A. Skiri"},"venue":null},"event_date":"2026-07-12T19:00:00+04:00","group_name":null,"status":"halftime","home_score":2,"away_score":0,"home_score_ht":2,"away_score_ht":0,"penalty_shootout":null,"extra_time_score":null,"current_minute":45,"period":"HT","home_xg_live":1.11,"away_xg_live":0.03,"incidents":[{"text":"HT","type":"period","minute":45,"is_live":false,"added_time":999,"away_score":0,"home_score":2},{"type":"substitution","minute":45,"is_home":false,"player_in":"H. Haugen","added_time":null,"player_out":"F. Flex","player_in_id":1561343,"player_out_id":2040138},{"type":"injuryTime","length":4,"minute":45},{"type":"goal","minute":31,"player":"D. Ďuriš","is_home":true,"sequence":[{"pid":98199,"pos":{"x":28.1,"y":8.8},"event":"ball-touch","player":"J. Svensson"},{"end":{"x":44.7,"y":50.6},"pid":1516451,"pos":{"x":44.9,"y":38},"event":"pass","player":"M. Bomholt"},{"end":{"x":56.9,"y":83.2},"pid":136170,"pos":{"x":44.7,"y":50.6},"event":"pass","player":"O. Selnaes"},{"end":{"x":81.3,"y":88.7},"pid":894245,"pos":{"x":60.3,"y":83.2},"event":"pass","player":"A. Pereira"},{"pid":933263,"pos":{"x":81.3,"y":88.7},"event":"ball-movement","player":"E. Ceide"},{"gm":{"x":56.45,"y":63},"pid":933263,"pos":{"x":87.3,"y":70.2},"event":"save","player":"E. Ceide"},{"gk":{"x":98.6,"y":48.4},"gm":{"x":71.51,"y":95.83},"pid":953583,"pos":{"x":89.3,"y":38.5},"body":"right-foot","event":"goal","player":"D. Ďuriš"}],"goal_type":"regular","player_id":953583,"added_time":null,"away_score":0,"home_score":2},{"type":"goal","minute":25,"player":"J. Svensson","is_home":true,"sequence":[{"gk":{"x":98.6,"y":49.8},"gm":{"x":70.43,"y":81},"pid":98199,"pos":{"x":83.1,"y":51},"body":"left-foot","event":"goal","player":"J. Svensson"}],"goal_type":"regular","player_id":98199,"added_time":null,"away_score":0,"home_score":1}],"live_stats":{"away":{"duels":47,"fouls":9,"passes":109,"crosses":"1/5 (0%)","tackles":10,"dribbles":"3/8 (38%)","offsides":1,"big_saves":1,"throw_ins":17,"clearances":16,"free_kicks":7,"goal_kicks":4,"long_balls":"8/29 (28%)","recoveries":18,"big_chances":0,"tackles_won":40,"total_saves":5,"total_shots":1,"aerial_duels":"2/8 (25%)","corner_kicks":2,"dispossessed":3,"ground_duels":"20/38 (53%)","hit_woodwork":0,"blocked_shots":1,"interceptions":7,"total_tackles":10,"expected_goals":0.03,"accurate_passes":71,"ball_possession":26,"goals_prevented":-0.65,"shots_on_target":0,"goalkeeper_saves":5,"shots_inside_box":1,"shots_off_target":0,"final_third_phase":"18/36 (50%)","shots_outside_box":0,"big_chances_missed":0,"big_chances_scored":0,"final_third_entries":29,"fouled_in_final_third":0,"touches_in_penalty_area":3},"home":{"duels":53,"fouls":7,"passes":318,"crosses":"2/9 (22%)","tackles":8,"dribbles":"1/8 (13%)","offsides":0,"big_saves":0,"throw_ins":8,"clearances":17,"free_kicks":9,"goal_kicks":0,"long_balls":"10/21 (48%)","recoveries":24,"big_chances":2,"tackles_won":75,"total_saves":0,"total_shots":11,"aerial_duels":"6/8 (75%)","corner_kicks":4,"dispossessed":2,"ground_duels":"18/37 (49%)","hit_woodwork":1,"blocked_shots":1,"interceptions":4,"total_tackles":8,"expected_goals":1.11,"accurate_passes":280,"ball_possession":74,"goals_prevented":0.0,"shots_on_target":7,"goalkeeper_saves":0,"shots_inside_box":7,"shots_off_target":3,"final_third_phase":"83/107 (78%)","shots_outside_box":4,"big_chances_missed":1,"big_chances_scored":1,"final_third_entries":41,"fouled_in_final_third":2,"touches_in_penalty_area":20},"first_half":{"away":{"duels":47,"fouls":9,"passes":109,"crosses":"1/5 (0%)","tackles":10,"dribbles":"3/8 (38%)","offsides":1,"throw_ins":17,"clearances":16,"free_kicks":7,"goal_kicks":4,"long_balls":"8/29 (28%)","recoveries":18,"big_chances":0,"tackles_won":40,"total_saves":5,"total_shots":1,"aerial_duels":"2/8 (25%)","corner_kicks":2,"dispossessed":3,"ground_duels":"20/38 (53%)","hit_woodwork":0,"blocked_shots":1,"interceptions":7,"total_tackles":10,"expected_goals":0.03,"accurate_passes":71,"ball_possession":26,"shots_on_target":0,"goalkeeper_saves":5,"shots_inside_box":1,"shots_off_target":0,"shots_outside_box":0,"big_chances_missed":0,"big_chances_scored":0,"final_third_entries":29,"fouled_in_final_third":0},"home":{"duels":53,"fouls":7,"passes":318,"crosses":"2/9 (22%)","tackles":8,"dribbles":"1/8 (13%)","offsides":0,"throw_ins":8,"clearances":17,"free_kicks":9,"goal_kicks":0,"long_balls":"10/21 (48%)","recoveries":24,"big_chances":2,"tackles_won":75,"total_saves":0,"total_shots":11,"aerial_duels":"6/8 (75%)","corner_kicks":4,"dispossessed":2,"ground_duels":"18/37 (49%)","hit_woodwork":1,"blocked_shots":1,"interceptions":4,"total_tackles":8,"expected_goals":1.11,"accurate_passes":280,"ball_possession":74,"shots_on_target":7,"goalkeeper_saves":0,"shots_inside_box":7,"shots_off_target":3,"shots_outside_box":4,"big_chances_missed":1,"big_chances_scored":1,"final_third_entries":41,"fouled_in_final_third":2}}}},{"id":207008,"league":{"id":54,"name":"Eliteserien","country":"Norway","is_women":false,"current_season":{"id":1230,"name":"Eliteserien 2026","year":2026,"start_date":"2026-01-01","end_date":"2026-12-31"}},"home_team":"SK Brann","away_team":"IK Start","home_team_obj":{"id":141,"name":"SK Brann","short_name":"Brann","country":"Norway","coach":{"name":"Eirik Horneland","shortName":"E. Horneland"},"venue":{"id":139,"name":"Brann Stadion","city":"Bergen","country":"Norway","capacity":17686}},"away_team_obj":{"id":2083,"name":"IK Start","short_name":"IK Start","country":"Norway","coach":{"name":"Azar Karadas","shortName":"A. Karadas"},"venue":null},"event_date":"2026-07-12T19:00:00+04:00","group_name":null,"status":"halftime","home_score":0,"away_score":0,"home_score_ht":0,"away_score_ht":0,"penalty_shootout":null,"extra_time_score":null,"current_minute":45,"period":"HT","home_xg_live":0.31,"away_xg_live":0.34,"incidents":[{"text":"HT","type":"period","minute":45,"is_live":false,"added_time":999,"away_score":0,"home_score":0},{"type":"injuryTime","length":1,"minute":45}],"live_stats":{"away":{"duels":65,"fouls":7,"passes":169,"crosses":"0/3 (0%)","tackles":14,"dribbles":"4/8 (50%)","throw_ins":9,"clearances":9,"free_kicks":4,"goal_kicks":4,"long_balls":"23/45 (51%)","recoveries":26,"big_chances":1,"tackles_won":71,"total_shots":6,"aerial_duels":"14/18 (78%)","corner_kicks":1,"dispossessed":3,"ground_duels":"22/37 (59%)","hit_woodwork":0,"blocked_shots":2,"interceptions":7,"total_tackles":14,"expected_goals":0.34,"accurate_passes":118,"ball_possession":34,"shots_on_target":0,"shots_inside_box":4,"shots_off_target":4,"final_third_phase":"21/44 (48%)","shots_outside_box":2,"big_chances_missed":1,"final_third_entries":30,"fouled_in_final_third":0,"touches_in_penalty_area":8},"home":{"duels":33,"fouls":4,"passes":330,"crosses":"3/7 (43%)","tackles":6,"dribbles":"1/10 (10%)","throw_ins":16,"clearances":10,"free_kicks":7,"goal_kicks":5,"long_balls":"17/40 (43%)","recoveries":22,"big_chances":1,"tackles_won":100,"total_shots":3,"aerial_duels":"4/18 (22%)","corner_kicks":1,"dispossessed":6,"ground_duels":"14/37 (38%)","hit_woodwork":0,"blocked_shots":0,"interceptions":1,"total_tackles":6,"expected_goals":0.31,"accurate_passes":280,"ball_possession":66,"shots_on_target":0,"shots_inside_box":3,"shots_off_target":3,"final_third_phase":"63/85 (74%)","shots_outside_box":0,"big_chances_missed":1,"final_third_entries":33,"fouled_in_final_third":1,"touches_in_penalty_area":9},"first_half":{"away":{"duels":65,"fouls":7,"passes":169,"crosses":"0/3 (0%)","tackles":14,"dribbles":"4/8 (50%)","throw_ins":9,"clearances":9,"free_kicks":4,"goal_kicks":4,"long_balls":"23/45 (51%)","recoveries":26,"big_chances":1,"tackles_won":71,"total_shots":6,"aerial_duels":"14/18 (78%)","corner_kicks":1,"dispossessed":3,"ground_duels":"22/37 (59%)","hit_woodwork":0,"blocked_shots":2,"interceptions":7,"total_tackles":14,"expected_goals":0.34,"accurate_passes":118,"ball_possession":34,"shots_on_target":0,"shots_inside_box":4,"shots_off_target":4,"shots_outside_box":2,"big_chances_missed":1,"final_third_entries":30,"fouled_in_final_third":0},"home":{"duels":33,"fouls":4,"passes":330,"crosses":"3/7 (43%)","tackles":6,"dribbles":"1/10 (10%)","throw_ins":16,"clearances":10,"free_kicks":7,"goal_kicks":5,"long_balls":"17/40 (43%)","recoveries":22,"big_chances":1,"tackles_won":100,"total_shots":3,"aerial_duels":"4/18 (22%)","corner_kicks":1,"dispossessed":6,"ground_duels":"14/37 (38%)","hit_woodwork":0,"blocked_shots":0,"interceptions":1,"total_tackles":6,"expected_goals":0.31,"accurate_passes":280,"ball_possession":66,"shots_on_target":0,"shots_inside_box":3,"shots_off_target":3,"shots_outside_box":0,"big_chances_missed":1,"final_third_entries":33,"fouled_in_final_third":1}}}}]