[{"id":218929,"league":{"id":79,"name":"Club Friendlies","country":"World","is_women":false,"current_season":null},"home_team":"Świt Skolwin Szczecin","away_team":"Błękitni Stargard","home_team_obj":{"id":1764,"name":"Świt Skolwin Szczecin","short_name":"Świt Szczecin","country":"Poland","coach":{"name":"Marcin Sasal","shortName":"M. Sasal"},"venue":null},"away_team_obj":{"id":4627,"name":"Błękitni Stargard","short_name":"Błękitni","country":"Poland","coach":null,"venue":null},"event_date":"2026-07-17T15:00:00+04:00","group_name":null,"status":"1st_half","home_score":0,"away_score":0,"home_score_ht":null,"away_score_ht":null,"penalty_shootout":null,"extra_time_score":null,"current_minute":39,"period":"1T","home_xg_live":null,"away_xg_live":null,"incidents":[{"text":"First half","type":"period","minute":45,"is_live":true,"added_time":999,"away_score":0,"home_score":0}],"live_stats":null},{"id":218922,"league":{"id":79,"name":"Club Friendlies","country":"World","is_women":false,"current_season":null},"home_team":"AaB","away_team":"Silkeborg IF","home_team_obj":{"id":3700,"name":"AaB","short_name":"Aalborg","country":"Denmark","coach":{"name":"Steffen Hojer","shortName":"S. Hojer"},"venue":null},"away_team_obj":{"id":1374,"name":"Silkeborg IF","short_name":"Silkeborg","country":"Denmark","coach":{"name":"Morten Dahm Kjærgaard","shortName":"M. D. Kjærgaard"},"venue":{"id":829,"name":"JYSK Park","city":"Silkeborg","country":"Denmark","capacity":10000}},"event_date":"2026-07-17T15:00:00+04:00","group_name":null,"status":"2nd_half","home_score":1,"away_score":2,"home_score_ht":0,"away_score_ht":2,"penalty_shootout":null,"extra_time_score":null,"current_minute":80,"period":"2T","home_xg_live":null,"away_xg_live":null,"incidents":[{"text":"Second half","type":"period","minute":90,"is_live":true,"added_time":999,"away_score":2,"home_score":1},{"type":"goal","minute":69,"player":"Unknown","is_home":true,"goal_type":"regular","player_id":null,"added_time":null,"away_score":2,"home_score":1},{"text":"HT","type":"period","minute":45,"is_live":false,"added_time":999,"away_score":2,"home_score":0},{"type":"card","minute":23,"player":"Unknown","is_home":false,"card_type":"yellow","player_id":null,"added_time":null},{"type":"card","minute":20,"player":"Unknown","is_home":true,"card_type":"yellow","player_id":null,"added_time":null},{"type":"goal","minute":16,"player":"Unknown","is_home":false,"goal_type":"regular","player_id":null,"added_time":null,"away_score":2,"home_score":0},{"type":"goal","minute":3,"player":"R. Al Hajj","is_home":false,"goal_type":"regular","player_id":978289,"added_time":null,"away_score":1,"home_score":0}],"live_stats":{"away":{"offsides":0,"red_cards":0,"throw_ins":0,"free_kicks":0,"goal_kicks":0,"corner_kicks":1,"yellow_cards":1,"ball_possession":50},"home":{"offsides":0,"red_cards":0,"throw_ins":0,"free_kicks":0,"goal_kicks":0,"corner_kicks":1,"yellow_cards":2,"ball_possession":50}}},{"id":205833,"league":{"id":52,"name":"Chinese Super League","country":"China","is_women":false,"current_season":{"id":1040,"name":"Chinese Super League 2026","year":2026,"start_date":"2026-01-01","end_date":"2026-12-31"}},"home_team":"Qingdao West Coast","away_team":"Chengdu Rongcheng","home_team_obj":{"id":2042,"name":"Qingdao West Coast","short_name":"Qingdao ","country":"China","coach":{"name":"Zhi Zheng","shortName":"Z. Zheng"},"venue":null},"away_team_obj":{"id":2029,"name":"Chengdu Rongcheng","short_name":"Chengdu","country":"China","coach":{"name":"John Aloisi","shortName":"J. Aloisi"},"venue":null},"event_date":"2026-07-17T15:00:00+04:00","group_name":null,"status":"2nd_half","home_score":1,"away_score":1,"home_score_ht":1,"away_score_ht":0,"penalty_shootout":null,"extra_time_score":null,"current_minute":81,"period":"2T","home_xg_live":null,"away_xg_live":null,"incidents":[{"text":"Second half","type":"period","minute":90,"is_live":true,"added_time":999,"away_score":1,"home_score":1},{"type":"goal","minute":76,"player":"F. Silva","is_home":false,"sequence":[{"gk":{"x":1,"y":49.8},"gm":{"x":64.52,"y":92.67},"pid":866588,"pos":{"x":12.9,"y":46},"body":"left-foot","event":"goal","player":"F. Silva"}],"goal_type":"regular","player_id":866588,"added_time":null,"away_score":1,"home_score":1},{"type":"card","minute":74,"player":"Davidson","is_home":true,"card_type":"yellow","player_id":814334,"added_time":null},{"type":"substitution","minute":70,"is_home":true,"player_in":"S. Jin","added_time":null,"player_out":"E. Lohman","player_in_id":2049875,"player_out_id":2084778},{"type":"card","minute":68,"player":"Y. Ming-Yang","is_home":false,"card_type":"yellow","player_id":335785,"added_time":null},{"type":"substitution","minute":64,"is_home":true,"player_in":"C. Zhang","added_time":null,"player_out":"Z. Yang","player_in_id":101550,"player_out_id":2474284},{"type":"substitution","minute":58,"is_home":false,"player_in":"W. Dongsheng","added_time":null,"player_out":"H. Hetao","player_in_id":876151,"player_out_id":1381654},{"type":"substitution","minute":58,"is_home":false,"player_in":"Rômulo","added_time":null,"player_out":"W. Ziming","player_in_id":609730,"player_out_id":878397},{"type":"card","minute":52,"player":"W. Shihao","is_home":false,"card_type":"yellow","player_id":584602,"added_time":null},{"type":"substitution","minute":46,"is_home":false,"player_in":"F. Silva","added_time":null,"player_out":"B. Abuduwaili","player_in_id":866588,"player_out_id":1210247},{"text":"HT","type":"period","minute":45,"is_live":false,"added_time":999,"away_score":0,"home_score":1},{"type":"injuryTime","length":3,"minute":45},{"type":"card","minute":41,"player":"Y. Dong","is_home":true,"card_type":"yellow","player_id":806480,"added_time":null},{"type":"card","minute":34,"player":"E. Lohman","is_home":true,"card_type":"yellow","player_id":2084778,"added_time":null},{"type":"goal","minute":23,"player":"N. Luz","is_home":true,"sequence":[{"gk":{"x":91,"y":43.3},"gm":{"x":35.48,"y":80},"pid":841743,"pos":{"x":85.3,"y":36.9},"body":"left-foot","event":"goal","player":"N. Luz"}],"goal_type":"regular","player_id":841743,"added_time":null,"away_score":0,"home_score":1},{"type":"varDecision","minute":4,"player":"W. Silva","is_home":false,"decision":"goalAwarded","confirmed":false,"player_id":121264,"added_time":null}],"live_stats":{"away":{"duels":51,"fouls":13,"passes":454,"crosses":"8/19 (42%)","punches":1,"tackles":18,"dribbles":"6/12 (50%)","offsides":4,"throw_ins":13,"clearances":19,"free_kicks":16,"goal_kicks":6,"long_balls":"18/36 (50%)","recoveries":37,"big_chances":1,"tackles_won":50,"total_saves":1,"total_shots":11,"aerial_duels":"10/20 (50%)","corner_kicks":4,"dispossessed":9,"ground_duels":"40/78 (51%)","hit_woodwork":0,"yellow_cards":2,"blocked_shots":2,"interceptions":5,"total_tackles":18,"accurate_passes":398,"ball_possession":66,"shots_on_target":2,"goalkeeper_saves":1,"shots_inside_box":8,"shots_off_target":7,"final_third_phase":"92/125 (74%)","shots_outside_box":3,"big_chances_missed":1,"big_chances_scored":0,"final_third_entries":63,"errors_lead_to_a_goal":1,"fouled_in_final_third":4,"touches_in_penalty_area":21},"home":{"duels":49,"fouls":16,"passes":233,"crosses":"1/11 (9%)","punches":0,"tackles":15,"dribbles":"10/21 (48%)","offsides":1,"throw_ins":10,"clearances":26,"free_kicks":13,"goal_kicks":11,"long_balls":"28/52 (54%)","recoveries":36,"big_chances":1,"tackles_won":60,"total_saves":2,"total_shots":9,"aerial_duels":"10/20 (50%)","corner_kicks":1,"dispossessed":7,"ground_duels":"39/79 (49%)","hit_woodwork":0,"yellow_cards":3,"blocked_shots":3,"interceptions":10,"total_tackles":15,"accurate_passes":180,"ball_possession":34,"shots_on_target":2,"goalkeeper_saves":2,"shots_inside_box":6,"shots_off_target":4,"final_third_phase":"43/72 (60%)","shots_outside_box":3,"big_chances_missed":0,"big_chances_scored":1,"final_third_entries":42,"errors_lead_to_a_goal":1,"fouled_in_final_third":2,"touches_in_penalty_area":16},"first_half":{"away":{"duels":44,"fouls":7,"passes":286,"crosses":"5/10 (50%)","tackles":9,"dribbles":"4/9 (44%)","offsides":3,"throw_ins":8,"clearances":9,"free_kicks":6,"goal_kicks":3,"long_balls":"6/17 (35%)","recoveries":21,"big_chances":1,"tackles_won":56,"total_saves":1,"total_shots":6,"aerial_duels":"3/9 (33%)","corner_kicks":2,"dispossessed":6,"ground_duels":"19/41 (46%)","hit_woodwork":0,"yellow_cards":0,"blocked_shots":2,"interceptions":4,"total_tackles":9,"accurate_passes":263,"ball_possession":68,"shots_on_target":1,"goalkeeper_saves":1,"shots_inside_box":3,"shots_off_target":3,"shots_outside_box":3,"big_chances_missed":1,"big_chances_scored":0,"final_third_entries":39,"fouled_in_final_third":2},"home":{"duels":56,"fouls":6,"passes":134,"crosses":"1/5 (20%)","tackles":11,"dribbles":"4/8 (50%)","offsides":1,"throw_ins":6,"clearances":11,"free_kicks":7,"goal_kicks":5,"long_balls":"16/29 (55%)","recoveries":24,"big_chances":1,"tackles_won":45,"total_saves":1,"total_shots":5,"aerial_duels":"6/9 (67%)","corner_kicks":0,"dispossessed":5,"ground_duels":"22/41 (54%)","hit_woodwork":0,"yellow_cards":2,"blocked_shots":1,"interceptions":4,"total_tackles":11,"accurate_passes":109,"ball_possession":32,"shots_on_target":2,"goalkeeper_saves":1,"shots_inside_box":4,"shots_off_target":2,"shots_outside_box":1,"big_chances_missed":0,"big_chances_scored":1,"final_third_entries":25,"fouled_in_final_third":2}},"second_half":{"away":{"duels":57,"fouls":6,"passes":168,"crosses":"3/9 (33%)","tackles":9,"dribbles":"2/3 (67%)","offsides":1,"throw_ins":5,"clearances":10,"free_kicks":10,"goal_kicks":3,"long_balls":"12/19 (63%)","recoveries":16,"big_chances":0,"tackles_won":44,"total_saves":0,"total_shots":5,"aerial_duels":"7/11 (64%)","corner_kicks":2,"dispossessed":3,"ground_duels":"21/37 (57%)","hit_woodwork":0,"yellow_cards":2,"blocked_shots":0,"interceptions":1,"total_tackles":9,"accurate_passes":135,"ball_possession":63,"shots_on_target":1,"goalkeeper_saves":0,"shots_inside_box":5,"shots_off_target":4,"shots_outside_box":0,"big_chances_missed":0,"big_chances_scored":0,"final_third_entries":24,"fouled_in_final_third":2},"home":{"duels":43,"fouls":10,"passes":99,"crosses":"0/6 (0%)","tackles":4,"dribbles":"6/13 (46%)","offsides":0,"throw_ins":4,"clearances":15,"free_kicks":6,"goal_kicks":6,"long_balls":"12/23 (52%)","recoveries":12,"big_chances":0,"tackles_won":100,"total_saves":1,"total_shots":4,"aerial_duels":"4/11 (36%)","corner_kicks":1,"dispossessed":2,"ground_duels":"17/38 (45%)","hit_woodwork":0,"yellow_cards":1,"blocked_shots":2,"interceptions":6,"total_tackles":4,"accurate_passes":71,"ball_possession":37,"shots_on_target":0,"goalkeeper_saves":1,"shots_inside_box":2,"shots_off_target":2,"shots_outside_box":2,"big_chances_missed":0,"big_chances_scored":0,"final_third_entries":17,"fouled_in_final_third":0}}}},{"id":218931,"league":{"id":79,"name":"Club Friendlies","country":"World","is_women":false,"current_season":null},"home_team":"Feyenoord","away_team":"RC Sporting Charleroi","home_team_obj":{"id":138,"name":"Feyenoord","short_name":"Feyenoord","country":"Netherlands","coach":{"name":"Giovanni van Bronckhorst","shortName":"G. v. Bronckhorst"},"venue":{"id":136,"name":"De Kuip","city":"Rotterdam","country":"Netherlands","capacity":47500}},"away_team_obj":{"id":243,"name":"RC Sporting Charleroi","short_name":"Charleroi","country":"Belgium","coach":{"name":"Mario Kohnen","shortName":"M. Kohnen"},"venue":{"id":234,"name":"Stade du Pays de Charleroi","city":"Charleroi","country":"Belgium","capacity":15000}},"event_date":"2026-07-17T15:30:00+04:00","group_name":null,"status":"2nd_half","home_score":0,"away_score":0,"home_score_ht":0,"away_score_ht":0,"penalty_shootout":null,"extra_time_score":null,"current_minute":48,"period":"2T","home_xg_live":null,"away_xg_live":null,"incidents":[{"text":"Second half","type":"period","minute":90,"is_live":true,"added_time":999,"away_score":0,"home_score":0},{"type":"substitution","minute":46,"is_home":true,"player_in":"C. Tengstedt","added_time":null,"player_out":"N. Ferri","player_in_id":957937,"player_out_id":1196903},{"type":"substitution","minute":46,"is_home":true,"player_in":"J. Lotomba","added_time":null,"player_out":"G. Read","player_in_id":796279,"player_out_id":1388535},{"text":"HT","type":"period","minute":45,"is_live":false,"added_time":999,"away_score":0,"home_score":0},{"type":"injuryTime","length":2,"minute":45},{"type":"substitution","minute":34,"is_home":true,"player_in":"S. Steijn","added_time":null,"player_out":"S. v. Persie","player_in_id":944467,"player_out_id":1470002}],"live_stats":{"away":{"duels":53,"fouls":6,"passes":241,"crosses":"2/13 (15%)","punches":1,"tackles":3,"dribbles":"4/5 (80%)","offsides":3,"throw_ins":7,"clearances":9,"free_kicks":10,"goal_kicks":8,"long_balls":"15/27 (56%)","recoveries":15,"tackles_won":100,"total_saves":1,"total_shots":2,"aerial_duels":"2/6 (33%)","corner_kicks":3,"dispossessed":1,"ground_duels":"16/28 (57%)","hit_woodwork":0,"blocked_shots":0,"interceptions":6,"total_tackles":3,"accurate_passes":209,"ball_possession":45,"shots_on_target":0,"goalkeeper_saves":1,"shots_inside_box":1,"shots_off_target":2,"final_third_phase":"27/35 (77%)","shots_outside_box":1,"final_third_entries":11,"fouled_in_final_third":2,"touches_in_penalty_area":3},"home":{"duels":47,"fouls":10,"passes":297,"crosses":"0/12 (0%)","punches":2,"tackles":2,"dribbles":"4/7 (57%)","offsides":2,"throw_ins":4,"clearances":12,"free_kicks":6,"goal_kicks":2,"long_balls":"16/21 (76%)","recoveries":18,"tackles_won":100,"total_saves":0,"total_shots":4,"aerial_duels":"4/6 (67%)","corner_kicks":2,"dispossessed":0,"ground_duels":"12/28 (43%)","hit_woodwork":0,"blocked_shots":2,"interceptions":1,"total_tackles":2,"accurate_passes":270,"ball_possession":55,"shots_on_target":1,"goalkeeper_saves":0,"shots_inside_box":2,"shots_off_target":1,"final_third_phase":"65/82 (79%)","shots_outside_box":2,"final_third_entries":31,"fouled_in_final_third":1,"touches_in_penalty_area":13},"first_half":{"away":{"duels":53,"fouls":5,"passes":239,"crosses":"2/13 (15%)","tackles":2,"dribbles":"4/5 (80%)","offsides":3,"throw_ins":7,"clearances":5,"free_kicks":10,"goal_kicks":8,"long_balls":"15/25 (60%)","recoveries":15,"tackles_won":100,"total_saves":1,"total_shots":2,"aerial_duels":"2/6 (33%)","corner_kicks":3,"dispossessed":1,"ground_duels":"15/26 (58%)","hit_woodwork":0,"blocked_shots":0,"interceptions":6,"total_tackles":2,"accurate_passes":209,"ball_possession":49,"shots_on_target":0,"goalkeeper_saves":1,"shots_inside_box":1,"shots_off_target":2,"shots_outside_box":1,"final_third_entries":11,"fouled_in_final_third":2},"home":{"duels":47,"fouls":10,"passes":256,"crosses":"0/9 (0%)","tackles":2,"dribbles":"4/6 (67%)","offsides":2,"throw_ins":3,"clearances":12,"free_kicks":5,"goal_kicks":2,"long_balls":"15/19 (79%)","recoveries":18,"tackles_won":100,"total_saves":0,"total_shots":4,"aerial_duels":"4/6 (67%)","corner_kicks":1,"dispossessed":0,"ground_duels":"11/26 (42%)","hit_woodwork":0,"blocked_shots":2,"interceptions":1,"total_tackles":2,"accurate_passes":231,"ball_possession":51,"shots_on_target":1,"goalkeeper_saves":0,"shots_inside_box":2,"shots_off_target":1,"shots_outside_box":2,"final_third_entries":28,"fouled_in_final_third":1}},"second_half":{"away":{"duels":50,"fouls":1,"passes":2,"crosses":"0/0 (0%)","tackles":1,"dribbles":"0/0 (0%)","offsides":0,"throw_ins":0,"clearances":4,"free_kicks":0,"goal_kicks":0,"long_balls":"0/2 (0%)","recoveries":0,"tackles_won":100,"total_saves":0,"total_shots":0,"corner_kicks":0,"dispossessed":0,"ground_duels":"1/2 (50%)","hit_woodwork":0,"blocked_shots":0,"interceptions":0,"total_tackles":1,"accurate_passes":0,"ball_possession":4,"shots_on_target":0,"goalkeeper_saves":0,"shots_inside_box":0,"shots_off_target":0,"shots_outside_box":0,"final_third_entries":0,"fouled_in_final_third":0},"home":{"duels":50,"fouls":0,"passes":41,"crosses":"0/3 (0%)","tackles":0,"dribbles":"0/1 (0%)","offsides":0,"throw_ins":1,"clearances":0,"free_kicks":1,"goal_kicks":0,"long_balls":"1/2 (50%)","recoveries":0,"tackles_won":0,"total_saves":0,"total_shots":0,"corner_kicks":1,"dispossessed":0,"ground_duels":"1/2 (50%)","hit_woodwork":0,"blocked_shots":0,"interceptions":0,"total_tackles":0,"accurate_passes":39,"ball_possession":96,"shots_on_target":0,"goalkeeper_saves":0,"shots_inside_box":0,"shots_off_target":0,"shots_outside_box":0,"final_third_entries":3,"fouled_in_final_third":0}}}},{"id":205829,"league":{"id":52,"name":"Chinese Super League","country":"China","is_women":false,"current_season":{"id":1040,"name":"Chinese Super League 2026","year":2026,"start_date":"2026-01-01","end_date":"2026-12-31"}},"home_team":"Beijing Guoan","away_team":"Liaoning Tieren FC","home_team_obj":{"id":2044,"name":"Beijing Guoan","short_name":"Guoan","country":"China","coach":{"name":"Nick Montgomery","shortName":"N. Montgomery"},"venue":null},"away_team_obj":{"id":2032,"name":"Liaoning Tieren FC","short_name":"Tieren","country":"China","coach":{"name":"Jung Won Seo","shortName":"J. W. Seo"},"venue":null},"event_date":"2026-07-17T15:35:00+04:00","group_name":null,"status":"2nd_half","home_score":1,"away_score":0,"home_score_ht":1,"away_score_ht":0,"penalty_shootout":null,"extra_time_score":null,"current_minute":45,"period":"2T","home_xg_live":null,"away_xg_live":null,"incidents":[{"text":"Second half","type":"period","minute":90,"is_live":true,"added_time":999,"away_score":0,"home_score":1},{"text":"HT","type":"period","minute":45,"is_live":false,"added_time":999,"away_score":0,"home_score":1},{"type":"card","minute":45,"player":"Z. Hongfu","is_home":false,"card_type":"yellow","player_id":2489147,"added_time":null},{"type":"injuryTime","length":4,"minute":45},{"type":"substitution","minute":39,"is_home":true,"player_in":"A. Abduhamit","added_time":null,"player_out":"Y. He","player_in_id":920987,"player_out_id":977985},{"type":"goal","assist":"A. Konte","minute":24,"player":"S. Erjini'ao","is_home":true,"sequence":[{"end":{"x":44.3,"y":55.4},"pid":926823,"pos":{"x":30.6,"y":66.7},"event":"pass","player":"Dawhan"},{"end":{"x":43.1,"y":50.9},"pid":979120,"pos":{"x":44.3,"y":55.4},"event":"pass","player":"A. Konte"},{"end":{"x":56.4,"y":51.3},"pid":837300,"pos":{"x":43.1,"y":50.9},"event":"pass","player":"B. Nkololo"},{"end":{"x":85.1,"y":58.2},"pid":979120,"pos":{"x":56.4,"y":51.3},"event":"ball-movement","player":"A. Konte"},{"end":{"x":85.1,"y":58.2},"pid":979120,"pos":{"x":84.4,"y":53.4},"event":"pass","player":"A. Konte"},{"pid":979120,"pos":{"x":85.1,"y":58.2},"event":"ball-movement","player":"A. Konte"},{"pid":979120,"pos":{"x":25.6,"y":41.9},"event":"ball-touch","assist":true,"player":"A. Konte"},{"gk":{"x":99.1,"y":51.6},"gm":{"x":63.98,"y":88.33},"pid":843735,"pos":{"x":80.8,"y":63.6},"body":"left-foot","event":"goal","player":"S. Erjini'ao"}],"goal_type":"regular","player_id":843735,"added_time":null,"away_score":0,"home_score":1}],"live_stats":{"away":{"duels":40,"fouls":8,"passes":171,"crosses":"2/7 (29%)","punches":3,"tackles":2,"dribbles":"5/11 (45%)","offsides":1,"throw_ins":9,"clearances":8,"free_kicks":10,"goal_kicks":7,"long_balls":"11/34 (32%)","recoveries":25,"tackles_won":100,"total_saves":0,"total_shots":5,"aerial_duels":"4/17 (24%)","corner_kicks":4,"dispossessed":3,"ground_duels":"17/36 (47%)","hit_woodwork":0,"yellow_cards":1,"blocked_shots":3,"interceptions":5,"total_tackles":2,"accurate_passes":128,"ball_possession":40,"shots_on_target":1,"goalkeeper_saves":0,"shots_inside_box":3,"shots_off_target":1,"final_third_phase":"22/48 (46%)","shots_outside_box":2,"final_third_entries":38,"touches_in_penalty_area":5},"home":{"duels":60,"fouls":10,"passes":256,"crosses":"2/7 (29%)","punches":0,"tackles":9,"dribbles":"2/2 (100%)","offsides":0,"throw_ins":5,"clearances":7,"free_kicks":8,"goal_kicks":5,"long_balls":"8/22 (36%)","recoveries":30,"tackles_won":78,"total_saves":1,"total_shots":9,"aerial_duels":"13/17 (76%)","corner_kicks":3,"dispossessed":3,"ground_duels":"19/36 (53%)","hit_woodwork":0,"yellow_cards":0,"blocked_shots":3,"interceptions":1,"total_tackles":9,"accurate_passes":208,"ball_possession":60,"shots_on_target":1,"goalkeeper_saves":1,"shots_inside_box":5,"shots_off_target":5,"final_third_phase":"35/57 (61%)","shots_outside_box":4,"final_third_entries":22,"touches_in_penalty_area":15},"first_half":{"away":{"duels":40,"fouls":8,"passes":171,"crosses":"2/7 (29%)","tackles":2,"dribbles":"5/11 (45%)","offsides":1,"throw_ins":9,"clearances":8,"free_kicks":10,"goal_kicks":7,"long_balls":"11/34 (32%)","recoveries":25,"tackles_won":100,"total_saves":0,"total_shots":5,"aerial_duels":"4/17 (24%)","corner_kicks":4,"dispossessed":3,"ground_duels":"17/36 (47%)","hit_woodwork":0,"yellow_cards":1,"blocked_shots":3,"interceptions":5,"total_tackles":2,"accurate_passes":128,"ball_possession":40,"shots_on_target":1,"goalkeeper_saves":0,"shots_inside_box":3,"shots_off_target":1,"shots_outside_box":2,"final_third_entries":38},"home":{"duels":60,"fouls":10,"passes":256,"crosses":"2/7 (29%)","tackles":9,"dribbles":"2/2 (100%)","offsides":0,"throw_ins":5,"clearances":7,"free_kicks":8,"goal_kicks":5,"long_balls":"8/22 (36%)","recoveries":30,"tackles_won":78,"total_saves":1,"total_shots":9,"aerial_duels":"13/17 (76%)","corner_kicks":3,"dispossessed":3,"ground_duels":"19/36 (53%)","hit_woodwork":0,"yellow_cards":0,"blocked_shots":3,"interceptions":1,"total_tackles":9,"accurate_passes":208,"ball_possession":60,"shots_on_target":1,"goalkeeper_saves":1,"shots_inside_box":5,"shots_off_target":5,"shots_outside_box":4,"final_third_entries":22}}}},{"id":205830,"league":{"id":52,"name":"Chinese Super League","country":"China","is_women":false,"current_season":{"id":1040,"name":"Chinese Super League 2026","year":2026,"start_date":"2026-01-01","end_date":"2026-12-31"}},"home_team":"Henan FC","away_team":"Qingdao Hainiu","home_team_obj":{"id":2038,"name":"Henan FC","short_name":"Henan","country":"China","coach":{"name":"Daniel Ramos","shortName":"D. Ramos"},"venue":null},"away_team_obj":{"id":2040,"name":"Qingdao Hainiu","short_name":"Hainiu","country":"China","coach":{"name":"Milan Ristic","shortName":"M. Ristic"},"venue":null},"event_date":"2026-07-17T15:35:00+04:00","group_name":null,"status":"2nd_half","home_score":2,"away_score":0,"home_score_ht":2,"away_score_ht":0,"penalty_shootout":null,"extra_time_score":null,"current_minute":45,"period":"2T","home_xg_live":null,"away_xg_live":null,"incidents":[{"text":"Second half","type":"period","minute":90,"is_live":true,"added_time":999,"away_score":0,"home_score":2},{"text":"HT","type":"period","minute":45,"is_live":false,"added_time":999,"away_score":0,"home_score":2},{"type":"injuryTime","length":4,"minute":45},{"type":"goal","assist":"A. Halik","minute":24,"player":"B. Nazário","is_home":true,"sequence":[{"pid":1031394,"pos":{"x":32.4,"y":43.7},"event":"interception","player":"A. Halik"},{"end":{"x":42,"y":46.1},"pid":1031394,"pos":{"x":28,"y":39.8},"event":"pass","assist":true,"player":"A. Halik"},{"pid":288247,"pos":{"x":42,"y":46.1},"body":"left-foot","event":"ball-movement","player":"B. Nazário"},{"gk":{"x":94.9,"y":50.4},"gm":{"x":72.58,"y":55.67},"pid":288247,"pos":{"x":70.2,"y":55.3},"body":"left-foot","event":"goal","player":"B. Nazário"}],"goal_type":"regular","player_id":288247,"added_time":null,"away_score":0,"home_score":2},{"type":"goal","assist":"B. Nazário","minute":19,"player":"I. Maidana","is_home":true,"sequence":[{"end":{"x":95.4,"y":49.4},"pid":288247,"pos":{"x":87.6,"y":12.5},"event":"cross","assist":true,"player":"B. Nazário"},{"gk":{"x":100,"y":49.3},"gm":{"x":65.05,"y":70.5},"pid":599686,"pos":{"x":95.4,"y":49.4},"body":"head","event":"goal","player":"I. Maidana"}],"goal_type":"regular","player_id":599686,"added_time":null,"away_score":0,"home_score":1}],"live_stats":{"away":{"duels":40,"fouls":4,"passes":179,"crosses":"2/11 (18%)","tackles":5,"dribbles":"3/6 (50%)","offsides":1,"big_saves":1,"throw_ins":10,"clearances":12,"free_kicks":3,"goal_kicks":8,"long_balls":"15/31 (48%)","recoveries":23,"big_chances":0,"tackles_won":80,"total_saves":3,"total_shots":4,"aerial_duels":"9/26 (35%)","corner_kicks":2,"dispossessed":6,"ground_duels":"11/24 (46%)","hit_woodwork":0,"blocked_shots":1,"interceptions":4,"total_tackles":5,"accurate_passes":137,"ball_possession":53,"shots_on_target":1,"goalkeeper_saves":3,"shots_inside_box":1,"shots_off_target":2,"final_third_phase":"23/43 (53%)","shots_outside_box":3,"big_chances_missed":0,"big_chances_scored":0,"final_third_entries":28,"fouled_in_final_third":2,"touches_in_penalty_area":4},"home":{"duels":60,"fouls":3,"passes":163,"crosses":"4/5 (80%)","tackles":9,"dribbles":"1/5 (20%)","offsides":2,"big_saves":0,"throw_ins":15,"clearances":20,"free_kicks":4,"goal_kicks":3,"long_balls":"13/22 (59%)","recoveries":24,"big_chances":3,"tackles_won":33,"total_saves":1,"total_shots":12,"aerial_duels":"17/26 (65%)","corner_kicks":3,"dispossessed":1,"ground_duels":"13/24 (54%)","hit_woodwork":0,"blocked_shots":1,"interceptions":7,"total_tackles":9,"accurate_passes":123,"ball_possession":47,"shots_on_target":5,"goalkeeper_saves":1,"shots_inside_box":10,"shots_off_target":6,"final_third_phase":"26/48 (54%)","shots_outside_box":2,"big_chances_missed":2,"big_chances_scored":1,"final_third_entries":26,"fouled_in_final_third":1,"touches_in_penalty_area":16},"first_half":{"away":{"duels":40,"fouls":4,"passes":179,"crosses":"2/11 (18%)","tackles":5,"dribbles":"3/6 (50%)","offsides":1,"throw_ins":10,"clearances":12,"free_kicks":3,"goal_kicks":8,"long_balls":"15/31 (48%)","recoveries":23,"big_chances":0,"tackles_won":80,"total_saves":3,"total_shots":4,"aerial_duels":"9/26 (35%)","corner_kicks":2,"dispossessed":6,"ground_duels":"11/24 (46%)","hit_woodwork":0,"blocked_shots":1,"interceptions":4,"total_tackles":5,"accurate_passes":137,"ball_possession":53,"shots_on_target":1,"goalkeeper_saves":3,"shots_inside_box":1,"shots_off_target":2,"shots_outside_box":3,"big_chances_missed":0,"big_chances_scored":0,"final_third_entries":28,"fouled_in_final_third":2},"home":{"duels":60,"fouls":3,"passes":163,"crosses":"4/5 (80%)","tackles":9,"dribbles":"1/5 (20%)","offsides":2,"throw_ins":15,"clearances":20,"free_kicks":4,"goal_kicks":3,"long_balls":"13/22 (59%)","recoveries":24,"big_chances":3,"tackles_won":33,"total_saves":1,"total_shots":12,"aerial_duels":"17/26 (65%)","corner_kicks":3,"dispossessed":1,"ground_duels":"13/24 (54%)","hit_woodwork":0,"blocked_shots":1,"interceptions":7,"total_tackles":9,"accurate_passes":123,"ball_possession":47,"shots_on_target":5,"goalkeeper_saves":1,"shots_inside_box":10,"shots_off_target":6,"shots_outside_box":2,"big_chances_missed":2,"big_chances_scored":1,"final_third_entries":26,"fouled_in_final_third":1}}}},{"id":218933,"league":{"id":79,"name":"Club Friendlies","country":"World","is_women":false,"current_season":null},"home_team":"De Graafschap","away_team":"SC Telstar","home_team_obj":{"id":1321,"name":"De Graafschap","short_name":"De Graafschap","country":"Netherlands","coach":{"name":"Thomas Duivenvoorden","shortName":"T. Duivenvoorden"},"venue":{"id":784,"name":"De Vijverberg","city":"Doetinchem","country":"Netherlands","capacity":12600}},"away_team_obj":{"id":179,"name":"SC Telstar","short_name":"Telstar","country":"Netherlands","coach":{"name":"Henk Brugge","shortName":"H. Brugge"},"venue":{"id":175,"name":"BUKO Stadion","city":"Velsen","country":"Netherlands","capacity":5336}},"event_date":"2026-07-17T16:00:00+04:00","group_name":null,"status":"1st_half","home_score":1,"away_score":1,"home_score_ht":null,"away_score_ht":null,"penalty_shootout":null,"extra_time_score":null,"current_minute":36,"period":"1T","home_xg_live":null,"away_xg_live":null,"incidents":[{"text":"First half","type":"period","minute":45,"is_live":true,"added_time":999,"away_score":1,"home_score":1},{"type":"goal","minute":31,"player":"S. Hetli","is_home":false,"goal_type":"regular","player_id":1548838,"added_time":null,"away_score":1,"home_score":1},{"type":"goal","minute":5,"player":"A. Darelas","is_home":true,"goal_type":"regular","player_id":1146304,"added_time":null,"away_score":0,"home_score":1}],"live_stats":{"away":{"offsides":0,"red_cards":0,"throw_ins":0,"free_kicks":1,"goal_kicks":0,"corner_kicks":4,"yellow_cards":0,"ball_possession":50},"home":{"offsides":0,"red_cards":0,"throw_ins":0,"free_kicks":0,"goal_kicks":0,"corner_kicks":2,"yellow_cards":0,"ball_possession":50}}},{"id":205831,"league":{"id":52,"name":"Chinese Super League","country":"China","is_women":false,"current_season":{"id":1040,"name":"Chinese Super League 2026","year":2026,"start_date":"2026-01-01","end_date":"2026-12-31"}},"home_team":"Yunnan Yukun","away_team":"Shanghai Port","home_team_obj":{"id":2039,"name":"Yunnan Yukun","short_name":"Yukun","country":"China","coach":{"name":"Jordi Vinyals","shortName":"J. Vinyals"},"venue":null},"away_team_obj":{"id":2037,"name":"Shanghai Port","short_name":"Port","country":"China","coach":{"name":"Kevin Muscat","shortName":"K. Muscat"},"venue":null},"event_date":"2026-07-17T16:00:00+04:00","group_name":null,"status":"1st_half","home_score":0,"away_score":2,"home_score_ht":null,"away_score_ht":null,"penalty_shootout":null,"extra_time_score":null,"current_minute":41,"period":"1T","home_xg_live":null,"away_xg_live":null,"incidents":[{"text":"First half","type":"period","minute":45,"is_live":true,"added_time":999,"away_score":2,"home_score":0},{"type":"goal","assist":"Leonardo","minute":40,"player":"Y. Xin","is_home":false,"sequence":[{"end":{"x":37.6,"y":11.9},"pid":923888,"pos":{"x":41.2,"y":0},"event":"throw-in","player":"P. Ampem"},{"pid":979522,"pos":{"x":36.6,"y":12.3},"event":"ball-touch","player":"Leonardo"},{"end":{"x":26.9,"y":60.3},"pid":1977665,"pos":{"x":55.9,"y":97.1},"event":"pass","player":"X. Y. Alex"},{"pid":923888,"pos":{"x":27,"y":60.2},"event":"ball-touch","player":"P. Ampem"},{"end":{"x":13.3,"y":33.7},"pid":979522,"pos":{"x":23,"y":49.4},"event":"pass","assist":true,"player":"Leonardo"},{"gk":{"x":0,"y":48.2},"gm":{"x":33.33,"y":60},"pid":817864,"pos":{"x":10.3,"y":36.2},"body":"right-foot","event":"goal","player":"Y. Xin"}],"goal_type":"regular","player_id":817864,"added_time":null,"away_score":2,"home_score":0},{"type":"goal","assist":"Ó. Melendo","minute":36,"player":"Z. Wei","is_home":false,"sequence":[{"end":{"x":27.4,"y":8.8},"pid":923888,"pos":{"x":38,"y":27.9},"event":"pass","player":"P. Ampem"},{"end":{"x":13.8,"y":49.5},"pid":861317,"pos":{"x":27.3,"y":8.5},"event":"cross","assist":true,"player":"Ó. Melendo"},{"gk":{"x":1.2,"y":49.8},"gm":{"x":72.58,"y":82},"pid":844086,"pos":{"x":13.8,"y":49.5},"body":"right-foot","event":"goal","player":"Z. Wei"}],"goal_type":"regular","player_id":844086,"added_time":null,"away_score":1,"home_score":0},{"type":"card","minute":11,"player":"Z. Huang","is_home":true,"card_type":"yellow","player_id":873898,"added_time":null}],"live_stats":{"away":{"duels":56,"fouls":6,"passes":140,"crosses":"1/7 (14%)","tackles":3,"dribbles":"3/3 (100%)","offsides":1,"big_saves":0,"throw_ins":7,"clearances":15,"free_kicks":4,"goal_kicks":5,"long_balls":"8/18 (44%)","recoveries":16,"big_chances":0,"tackles_won":67,"total_saves":1,"total_shots":5,"aerial_duels":"5/11 (45%)","corner_kicks":2,"dispossessed":1,"ground_duels":"10/16 (63%)","hit_woodwork":0,"yellow_cards":0,"blocked_shots":0,"interceptions":2,"total_tackles":3,"accurate_passes":118,"ball_possession":53,"shots_on_target":3,"goalkeeper_saves":1,"shots_inside_box":3,"shots_off_target":2,"final_third_phase":"21/34 (62%)","shots_outside_box":2,"big_chances_missed":0,"final_third_entries":19,"touches_in_penalty_area":8},"home":{"duels":44,"fouls":4,"passes":123,"crosses":"3/6 (50%)","tackles":1,"dribbles":"0/2 (0%)","offsides":2,"big_saves":1,"throw_ins":12,"clearances":6,"free_kicks":6,"goal_kicks":6,"long_balls":"7/16 (44%)","recoveries":13,"big_chances":1,"tackles_won":0,"total_saves":1,"total_shots":6,"aerial_duels":"6/11 (55%)","corner_kicks":4,"dispossessed":1,"ground_duels":"6/16 (38%)","hit_woodwork":0,"yellow_cards":1,"blocked_shots":3,"interceptions":6,"total_tackles":1,"accurate_passes":94,"ball_possession":47,"shots_on_target":1,"goalkeeper_saves":1,"shots_inside_box":3,"shots_off_target":2,"final_third_phase":"17/28 (61%)","shots_outside_box":3,"big_chances_missed":1,"final_third_entries":12,"touches_in_penalty_area":8},"first_half":{"away":{"duels":56,"fouls":6,"passes":140,"crosses":"1/7 (14%)","tackles":3,"dribbles":"3/3 (100%)","offsides":1,"throw_ins":7,"clearances":15,"free_kicks":4,"goal_kicks":5,"long_balls":"8/18 (44%)","recoveries":16,"big_chances":0,"tackles_won":67,"total_saves":1,"total_shots":5,"aerial_duels":"5/11 (45%)","corner_kicks":2,"dispossessed":1,"ground_duels":"10/16 (63%)","hit_woodwork":0,"yellow_cards":0,"blocked_shots":0,"interceptions":2,"total_tackles":3,"accurate_passes":118,"ball_possession":53,"shots_on_target":3,"goalkeeper_saves":1,"shots_inside_box":3,"shots_off_target":2,"shots_outside_box":2,"big_chances_missed":0,"final_third_entries":19},"home":{"duels":44,"fouls":4,"passes":123,"crosses":"3/6 (50%)","tackles":1,"dribbles":"0/2 (0%)","offsides":2,"throw_ins":12,"clearances":6,"free_kicks":6,"goal_kicks":6,"long_balls":"7/16 (44%)","recoveries":13,"big_chances":1,"tackles_won":0,"total_saves":1,"total_shots":6,"aerial_duels":"6/11 (55%)","corner_kicks":4,"dispossessed":1,"ground_duels":"6/16 (38%)","hit_woodwork":0,"yellow_cards":1,"blocked_shots":3,"interceptions":6,"total_tackles":1,"accurate_passes":94,"ball_possession":47,"shots_on_target":1,"goalkeeper_saves":1,"shots_inside_box":3,"shots_off_target":2,"shots_outside_box":3,"big_chances_missed":1,"final_third_entries":12}}}},{"id":218942,"league":{"id":79,"name":"Club Friendlies","country":"World","is_women":false,"current_season":null},"home_team":"FC Midtjylland","away_team":"Odense Boldklub","home_team_obj":{"id":127,"name":"FC Midtjylland","short_name":"Midtjylland","country":"Denmark","coach":{"name":"Mike Tullberg","shortName":"M. Tullberg"},"venue":{"id":125,"name":"MCH Arena","city":"Herning","country":"Denmark","capacity":11809}},"away_team_obj":{"id":3120,"name":"Odense Boldklub","short_name":"OB","country":"Denmark","coach":{"name":"Alexander Zorniger","shortName":"A. Zorniger"},"venue":null},"event_date":"2026-07-17T18:00:00+04:00","group_name":null,"status":"1st_half","home_score":3,"away_score":1,"home_score_ht":null,"away_score_ht":null,"penalty_shootout":null,"extra_time_score":null,"current_minute":42,"period":"1T","home_xg_live":null,"away_xg_live":null,"incidents":[{"text":"First half","type":"period","minute":45,"is_live":true,"added_time":999,"away_score":1,"home_score":3},{"type":"goal","minute":37,"player":"F. Etim","is_home":true,"goal_type":"regular","player_id":1172464,"added_time":null,"away_score":1,"home_score":3},{"type":"goal","minute":34,"player":"F. Etim","is_home":true,"goal_type":"regular","player_id":1172464,"added_time":null,"away_score":1,"home_score":2},{"type":"goal","minute":31,"player":"A. Sørensen","is_home":false,"goal_type":"regular","player_id":926558,"added_time":null,"away_score":1,"home_score":1},{"type":"card","minute":27,"player":"J. Berthel Askou","is_home":false,"card_type":"yellow","player_id":929599,"added_time":null},{"type":"goal","minute":14,"player":"F. Djú","is_home":true,"goal_type":"regular","player_id":1146009,"added_time":null,"away_score":0,"home_score":1}],"live_stats":{"away":{"yellow_cards":1},"home":{"yellow_cards":0}}}]