[{"id":211506,"league":{"id":19,"name":"Liga MX Apertura","country":"Mexico","is_women":false,"current_season":{"id":1309,"name":"Liga MX, Apertura 2026","year":2026,"start_date":"2026-01-01","end_date":"2026-12-31"}},"home_team":"Querétaro FC","away_team":"Club América","home_team_obj":{"id":309,"name":"Querétaro FC","short_name":"Querétaro","country":"Mexico","coach":{"name":"Esteban Gonzalez","shortName":"E. Gonzalez"},"venue":{"id":297,"name":"Estadio La Corregidora","city":"Santiago de Queretaro","country":"Mexico","capacity":34130}},"away_team_obj":{"id":307,"name":"Club América","short_name":"América","country":"Mexico","coach":{"name":"Guillermo Almada","shortName":"G. Almada"},"venue":{"id":295,"name":"Estadio Azteca","city":"Mexico City","country":"Mexico","capacity":87523}},"event_date":"2026-07-19T07:10:00+04:00","group_name":null,"status":"2nd_half","home_score":0,"away_score":0,"home_score_ht":0,"away_score_ht":0,"penalty_shootout":null,"extra_time_score":null,"current_minute":73,"period":"2T","home_xg_live":0.74,"away_xg_live":1.66,"incidents":[{"text":"Second half","type":"period","minute":90,"is_live":true,"added_time":999,"away_score":0,"home_score":0},{"type":"card","minute":71,"player":"D. Reyes","is_home":true,"card_type":"yellow","player_id":139421,"added_time":null},{"type":"card","minute":70,"player":"R. Juárez","is_home":false,"card_type":"yellow","player_id":993076,"added_time":null},{"type":"card","minute":70,"player":"L. Abascia","is_home":true,"card_type":"yellow","player_id":1113113,"added_time":null},{"type":"varDecision","minute":67,"player":"M. Vázquez","is_home":false,"decision":"penaltyNotAwarded","confirmed":false,"player_id":1218833,"added_time":null},{"type":"card","minute":65,"player":"B. Duarte","is_home":true,"card_type":"yellow","player_id":1545648,"added_time":null},{"type":"substitution","minute":59,"is_home":true,"player_in":"P. Victor","added_time":null,"player_out":"J. P. Cázares","player_in_id":1108505,"player_out_id":2445423},{"type":"substitution","minute":59,"is_home":true,"player_in":"E. Giménez","added_time":null,"player_out":"J. Unjanque","player_in_id":927326,"player_out_id":1902031},{"text":"HT","type":"period","minute":45,"is_live":false,"added_time":999,"away_score":0,"home_score":0},{"type":"injuryTime","length":3,"minute":45},{"type":"card","minute":42,"player":"K. Álvarez","is_home":false,"card_type":"yellow","player_id":929848,"added_time":null},{"type":"card","minute":27,"player":"A. Cervantes","is_home":false,"card_type":"yellow","player_id":804345,"added_time":null},{"type":"card","minute":23,"player":"S. Homenchenko","is_home":true,"card_type":"yellow","player_id":1086252,"added_time":null}],"live_stats":{"away":{"duels":56,"fouls":7,"passes":321,"crosses":"6/20 (30%)","punches":1,"tackles":13,"dribbles":"3/10 (30%)","offsides":0,"big_saves":0,"throw_ins":10,"clearances":16,"free_kicks":6,"goal_kicks":9,"long_balls":"24/45 (53%)","recoveries":32,"big_chances":0,"high_claims":1,"tackles_won":92,"total_saves":2,"total_shots":13,"aerial_duels":"13/21 (62%)","corner_kicks":7,"dispossessed":3,"ground_duels":"21/40 (53%)","hit_woodwork":0,"yellow_cards":3,"blocked_shots":6,"interceptions":3,"penalty_saves":0,"total_tackles":13,"expected_goals":0.87,"accurate_passes":266,"ball_possession":64,"goals_prevented":0.23,"shots_on_target":3,"goalkeeper_saves":2,"shots_inside_box":7,"shots_off_target":4,"final_third_phase":"54/70 (77%)","shots_outside_box":6,"big_chances_missed":0,"final_third_entries":28,"errors_lead_to_a_shot":1,"fouled_in_final_third":2,"touches_in_penalty_area":17},"home":{"duels":44,"fouls":7,"passes":180,"crosses":"1/11 (9%)","punches":0,"tackles":11,"dribbles":"2/11 (18%)","offsides":5,"big_saves":1,"throw_ins":16,"clearances":14,"free_kicks":7,"goal_kicks":5,"long_balls":"15/35 (43%)","recoveries":34,"big_chances":2,"high_claims":0,"tackles_won":55,"total_saves":4,"total_shots":8,"aerial_duels":"8/21 (38%)","corner_kicks":2,"dispossessed":5,"ground_duels":"20/42 (48%)","hit_woodwork":0,"yellow_cards":4,"blocked_shots":1,"interceptions":3,"penalty_saves":1,"total_tackles":11,"expected_goals":0.72,"accurate_passes":130,"ball_possession":36,"goals_prevented":0.49,"shots_on_target":2,"goalkeeper_saves":4,"shots_inside_box":5,"shots_off_target":5,"final_third_phase":"40/68 (59%)","shots_outside_box":3,"big_chances_missed":2,"final_third_entries":36,"errors_lead_to_a_shot":0,"fouled_in_final_third":1,"touches_in_penalty_area":8},"first_half":{"away":{"duels":58,"fouls":6,"passes":244,"crosses":"5/13 (38%)","tackles":11,"dribbles":"3/7 (43%)","offsides":0,"throw_ins":4,"clearances":10,"free_kicks":5,"goal_kicks":7,"long_balls":"16/32 (50%)","recoveries":24,"big_chances":0,"tackles_won":91,"total_saves":1,"total_shots":11,"aerial_duels":"8/14 (57%)","corner_kicks":5,"dispossessed":1,"ground_duels":"18/31 (58%)","hit_woodwork":0,"yellow_cards":2,"blocked_shots":5,"interceptions":2,"total_tackles":11,"expected_goals":0.76,"accurate_passes":203,"ball_possession":63,"shots_on_target":2,"goalkeeper_saves":1,"shots_inside_box":7,"shots_off_target":4,"shots_outside_box":4,"big_chances_missed":0,"final_third_entries":19,"fouled_in_final_third":0},"home":{"duels":42,"fouls":5,"passes":146,"crosses":"1/6 (17%)","tackles":5,"dribbles":"2/9 (22%)","offsides":4,"throw_ins":12,"clearances":10,"free_kicks":6,"goal_kicks":4,"long_balls":"10/28 (36%)","recoveries":27,"big_chances":1,"tackles_won":60,"total_saves":2,"total_shots":5,"aerial_duels":"6/14 (43%)","corner_kicks":1,"dispossessed":4,"ground_duels":"13/31 (42%)","hit_woodwork":0,"yellow_cards":1,"blocked_shots":1,"interceptions":2,"total_tackles":5,"expected_goals":0.29,"accurate_passes":105,"ball_possession":37,"shots_on_target":1,"goalkeeper_saves":2,"shots_inside_box":2,"shots_off_target":3,"shots_outside_box":3,"big_chances_missed":1,"final_third_entries":27,"fouled_in_final_third":1}},"second_half":{"away":{"duels":50,"fouls":1,"passes":77,"crosses":"1/7 (14%)","tackles":2,"dribbles":"0/3 (0%)","offsides":0,"throw_ins":6,"clearances":6,"free_kicks":1,"goal_kicks":2,"long_balls":"8/13 (62%)","recoveries":8,"big_chances":0,"tackles_won":100,"total_saves":1,"total_shots":2,"aerial_duels":"5/7 (71%)","corner_kicks":2,"dispossessed":2,"ground_duels":"3/9 (33%)","hit_woodwork":0,"yellow_cards":1,"blocked_shots":1,"interceptions":1,"total_tackles":2,"expected_goals":0.11,"accurate_passes":63,"ball_possession":68,"shots_on_target":1,"goalkeeper_saves":1,"shots_inside_box":0,"shots_off_target":0,"shots_outside_box":2,"big_chances_missed":0,"final_third_entries":9,"fouled_in_final_third":2},"home":{"duels":50,"fouls":2,"passes":34,"crosses":"0/5 (0%)","tackles":6,"dribbles":"0/2 (0%)","offsides":1,"throw_ins":4,"clearances":4,"free_kicks":1,"goal_kicks":1,"long_balls":"5/7 (71%)","recoveries":7,"big_chances":1,"tackles_won":50,"total_saves":2,"total_shots":3,"aerial_duels":"2/7 (29%)","corner_kicks":1,"dispossessed":1,"ground_duels":"7/11 (64%)","hit_woodwork":0,"yellow_cards":3,"blocked_shots":0,"interceptions":1,"total_tackles":6,"expected_goals":0.43,"accurate_passes":25,"ball_possession":32,"shots_on_target":1,"goalkeeper_saves":2,"shots_inside_box":3,"shots_off_target":2,"shots_outside_box":0,"big_chances_missed":1,"final_third_entries":9,"fouled_in_final_third":0}}}}]