[{"id":212775,"league":{"id":53,"name":"Botola Pro","country":"Morocco","is_women":false,"current_season":null},"home_team":"Fath Union Sport","away_team":"RS Berkane","home_team_obj":{"id":2066,"name":"Fath Union Sport","short_name":"FUS Rabat","country":"Morocco","coach":{"name":"Saïd Chiba","shortName":"S. Chiba"},"venue":null},"away_team_obj":{"id":594,"name":"RS Berkane","short_name":"RS Berkane","country":"Morocco","coach":{"name":"Moïn Chaabani","shortName":"M. Chaabani"},"venue":{"id":472,"name":"Stade Municipal de Berkane","city":"Berkane","country":"Morocco","capacity":15000}},"event_date":"2026-06-28T21:00:00+04:00","group_name":null,"status":"1st_half","home_score":0,"away_score":0,"home_score_ht":null,"away_score_ht":null,"penalty_shootout":null,"extra_time_score":null,"current_minute":8,"period":"1T","home_xg_live":null,"away_xg_live":null,"incidents":[{"text":"First half","type":"period","minute":45,"is_live":true,"added_time":999,"away_score":0,"home_score":0}],"live_stats":null},{"id":212780,"league":{"id":53,"name":"Botola Pro","country":"Morocco","is_women":false,"current_season":null},"home_team":"Wydad Casablanca","away_team":"Olympique Dcheira","home_team_obj":{"id":2064,"name":"Wydad Casablanca","short_name":"WAC","country":"Morocco","coach":{"name":"Mohamed Benchrifa","shortName":"M. Benchrifa"},"venue":null},"away_team_obj":{"id":2063,"name":"Olympique Dcheira","short_name":"","country":"Morocco","coach":{"name":"Bouchaib El Moubarki","shortName":"B. E. Moubarki"},"venue":null},"event_date":"2026-06-28T21:00:00+04:00","group_name":null,"status":"1st_half","home_score":0,"away_score":1,"home_score_ht":null,"away_score_ht":null,"penalty_shootout":null,"extra_time_score":null,"current_minute":8,"period":"1T","home_xg_live":null,"away_xg_live":null,"incidents":[{"text":"First half","type":"period","minute":45,"is_live":true,"added_time":999,"away_score":1,"home_score":0},{"type":"goal","minute":8,"player":"Unknown","is_home":false,"goal_type":"regular","player_id":null,"added_time":null,"away_score":1,"home_score":0}],"live_stats":null},{"id":212774,"league":{"id":53,"name":"Botola Pro","country":"Morocco","is_women":false,"current_season":null},"home_team":"Difaâ Hassani El-Jadidi","away_team":"Kawkab Athletic Club Marrakech","home_team_obj":{"id":2069,"name":"Difaâ Hassani El-Jadidi","short_name":"DHJ","country":"Morocco","coach":{"name":"Rui Almeida","shortName":"R. Almeida"},"venue":null},"away_team_obj":{"id":2065,"name":"Kawkab Athletic Club Marrakech","short_name":"KACM","country":"Morocco","coach":{"name":"Hicham Dmiai","shortName":"H. Dmiai"},"venue":null},"event_date":"2026-06-28T21:00:00+04:00","group_name":null,"status":"1st_half","home_score":0,"away_score":0,"home_score_ht":null,"away_score_ht":null,"penalty_shootout":null,"extra_time_score":null,"current_minute":8,"period":"1T","home_xg_live":null,"away_xg_live":null,"incidents":[{"text":"First half","type":"period","minute":45,"is_live":true,"added_time":999,"away_score":0,"home_score":0},{"type":"card","minute":6,"player":"Y. Riani","is_home":false,"card_type":"yellow","player_id":1488437,"added_time":null},{"type":"card","minute":5,"player":"A. Ziani","is_home":true,"card_type":"yellow","player_id":1874639,"added_time":null},{"type":"card","minute":2,"player":"S. Cissé","is_home":false,"card_type":"yellow","player_id":1870410,"added_time":null}],"live_stats":null},{"id":212778,"league":{"id":53,"name":"Botola Pro","country":"Morocco","is_women":false,"current_season":null},"home_team":"MAS de Fès","away_team":"Union Sportive Yacoub El Mansour","home_team_obj":{"id":2071,"name":"MAS de Fès","short_name":"MAS","country":"Morocco","coach":{"name":"Pablo Franco","shortName":"P. Franco"},"venue":null},"away_team_obj":{"id":2068,"name":"Union Sportive Yacoub El Mansour","short_name":"USYM","country":"Morocco","coach":{"name":"Mehdi El Jabri","shortName":"M. E. Jabri"},"venue":null},"event_date":"2026-06-28T21:00:00+04:00","group_name":null,"status":"1st_half","home_score":0,"away_score":0,"home_score_ht":null,"away_score_ht":null,"penalty_shootout":null,"extra_time_score":null,"current_minute":8,"period":"1T","home_xg_live":null,"away_xg_live":null,"incidents":[{"text":"First half","type":"period","minute":45,"is_live":true,"added_time":999,"away_score":0,"home_score":0}],"live_stats":null},{"id":212773,"league":{"id":53,"name":"Botola Pro","country":"Morocco","is_women":false,"current_season":null},"home_team":"AS FAR Rabat","away_team":"Union Touarga Sport","home_team_obj":{"id":586,"name":"AS FAR Rabat","short_name":"AS FAR","country":"Morocco","coach":{"name":"Alexandre Santos","shortName":"A. Santos"},"venue":{"id":467,"name":"Complexe Sportif Moulay Abdellah","city":"Rabat","country":"Morocco","capacity":69700}},"away_team_obj":{"id":2062,"name":"Union Touarga Sport","short_name":"Union Touarga","country":"Morocco","coach":{"name":"Abdelouahed Zamrat","shortName":"A. Zamrat"},"venue":null},"event_date":"2026-06-28T21:00:00+04:00","group_name":null,"status":"1st_half","home_score":0,"away_score":0,"home_score_ht":null,"away_score_ht":null,"penalty_shootout":null,"extra_time_score":null,"current_minute":7,"period":"1T","home_xg_live":null,"away_xg_live":null,"incidents":[{"text":"First half","type":"period","minute":45,"is_live":true,"added_time":999,"away_score":0,"home_score":0}],"live_stats":null},{"id":212776,"league":{"id":53,"name":"Botola Pro","country":"Morocco","is_women":false,"current_season":null},"home_team":"Hassania d'Agadir","away_team":"Renaissance Zemamra","home_team_obj":{"id":2060,"name":"Hassania d'Agadir","short_name":"HUSA","country":"Morocco","coach":{"name":"Hilal Et-Tair","shortName":"H. Et-Tair"},"venue":null},"away_team_obj":{"id":2072,"name":"Renaissance Zemamra","short_name":"Renaissance Zemamra","country":"Morocco","coach":{"name":"Mehdi Mrani Alaoui","shortName":"M. M. Alaoui"},"venue":null},"event_date":"2026-06-28T21:00:00+04:00","group_name":null,"status":"1st_half","home_score":0,"away_score":0,"home_score_ht":null,"away_score_ht":null,"penalty_shootout":null,"extra_time_score":null,"current_minute":8,"period":"1T","home_xg_live":null,"away_xg_live":null,"incidents":[{"text":"First half","type":"period","minute":45,"is_live":true,"added_time":999,"away_score":0,"home_score":0}],"live_stats":null},{"id":212777,"league":{"id":53,"name":"Botola Pro","country":"Morocco","is_women":false,"current_season":null},"home_team":"Ittihad Tanger","away_team":"Raja Club Athletic","home_team_obj":{"id":2059,"name":"Ittihad Tanger","short_name":"Ittihad Tanger","country":"Morocco","coach":{"name":"Abdelhak Benchika","shortName":"A. Benchika"},"venue":null},"away_team_obj":{"id":2067,"name":"Raja Club Athletic","short_name":"Raja CA","country":"Morocco","coach":{"name":"Nasreddine Nabi","shortName":"N. Nabi"},"venue":null},"event_date":"2026-06-28T21:00:00+04:00","group_name":null,"status":"1st_half","home_score":0,"away_score":0,"home_score_ht":null,"away_score_ht":null,"penalty_shootout":null,"extra_time_score":null,"current_minute":7,"period":"1T","home_xg_live":null,"away_xg_live":null,"incidents":[{"text":"First half","type":"period","minute":45,"is_live":true,"added_time":999,"away_score":0,"home_score":0}],"live_stats":null},{"id":212779,"league":{"id":53,"name":"Botola Pro","country":"Morocco","is_women":false,"current_season":null},"home_team":"Olympic Safi","away_team":"CODM Meknès","home_team_obj":{"id":2061,"name":"Olympic Safi","short_name":"OC Safi","country":"Morocco","coach":{"name":"Mounir Jaouani","shortName":"M. Jaouani"},"venue":null},"away_team_obj":{"id":2070,"name":"CODM Meknès","short_name":"CODM","country":"Morocco","coach":{"name":"Abdelaziz Dnibi","shortName":"A. Dnibi"},"venue":null},"event_date":"2026-06-28T21:00:00+04:00","group_name":null,"status":"1st_half","home_score":1,"away_score":0,"home_score_ht":null,"away_score_ht":null,"penalty_shootout":null,"extra_time_score":null,"current_minute":5,"period":"1T","home_xg_live":null,"away_xg_live":null,"incidents":[{"text":"First half","type":"period","minute":45,"is_live":true,"added_time":999,"away_score":0,"home_score":1},{"type":"goal","minute":6,"player":"Unknown","is_home":true,"goal_type":"regular","player_id":null,"added_time":null,"away_score":0,"home_score":1}],"live_stats":null}]